{
  "type": "Feature",
  "properties": {
    "iso:country":"PY",
    "name:ita_x_preferred":[
        "R. I. Tres Corrales"
    ],
    "name:por_x_preferred":[
        "R. I. Tres Corrales"
    ],
    "name:spa_x_preferred":[
        "R. I. Tres Corrales"
    ],
    "name:zho_x_preferred":[
        "\u7279\u96f7\u65af\u79d1\u62c9\u840a\u65af"
    ],
    "qs:gn_country":"PY",
    "qs:gn_fcode":"PPL",
    "qs:gn_pop":252,
    "qs:name":"R. I. Tres Corrales",
    "qs:name_adm0":"Paraguay",
    "qs:name_adm1":"Caaguaz\u00fa",
    "qs:photos":0,
    "qs:photos_1k":0,
    "qs:photos_9k":0,
    "qs:photos_9r":0,
    "qs:photos_all":0,
    "qs:photos_sr":0,
    "qs:placetype":"Town",
    "qs:pop_sr":"2",
    "qs:woe_adm0":23424917,
    "wd:wordcount":19,
    "wof:name":"R. I. Tres Corrales",
    "wof:placetype":"locality",
    "wof:population":252
},
  "geometry": {"coordinates":[-56.13333,-25.03333],"type":"Point"}
}