{
  "type": "Feature",
  "properties": {
    "gn:admin1_code":"23.0",
    "gn:admin2_code":"1702",
    "gn:asciiname":"Estancia Laguna Leon",
    "gn:country_code":"PY",
    "gn:dem":100,
    "gn:feature_class":"P",
    "gn:feature_code":"PPL",
    "gn:name":"Estancia Laguna Le\u00f3n",
    "gn:population":0,
    "gn:timezone":"America/Asuncion",
    "iso:country":"PY",
    "wof:name":"Estancia Laguna Leon",
    "wof:placetype":"locality"
},
  "geometry": {"coordinates":[-58.75,-21.41667],"type":"Point"}
}