{
  "type": "Feature",
  "properties": {
    "gn:admin1_code":"2.0",
    "gn:admin2_code":"1303",
    "gn:asciiname":"Torora",
    "gn:country_code":"PY",
    "gn:dem":499,
    "gn:feature_class":"P",
    "gn:feature_code":"PPL",
    "gn:name":"Toror\u00e1",
    "gn:population":0,
    "gn:timezone":"America/Asuncion",
    "iso:country":"PY",
    "wof:name":"Torora",
    "wof:placetype":"locality"
},
  "geometry": {"coordinates":[-55.51667,-23.38333],"type":"Point"}
}