{
  "type": "Feature",
  "properties": {
    "gn:admin1_code":"17.0",
    "gn:admin2_code":"0210",
    "gn:asciiname":"Colonia Manitoba",
    "gn:country_code":"PY",
    "gn:dem":211,
    "gn:feature_class":"P",
    "gn:feature_code":"PPL",
    "gn:name":"Colonia Manitoba",
    "gn:population":0,
    "gn:timezone":"America/Asuncion",
    "iso:country":"PY",
    "name:spa_x_preferred":[
        "Colonia Manitoba"
    ],
    "wof:name":"Colonia Manitoba",
    "wof:placetype":"locality"
},
  "geometry": {"coordinates":[-56.56594000000001,-23.56813],"type":"Point"}
}