{
  "type": "Feature",
  "properties": {
    "gn:admin1_code":"17.0",
    "gn:admin2_code":"0204",
    "gn:asciiname":"Compania Jhugua Rey",
    "gn:country_code":"PY",
    "gn:dem":96,
    "gn:feature_class":"P",
    "gn:feature_code":"PPL",
    "gn:name":"Compa\u00f1\u00eda Jhugu\u00e1 Rey",
    "gn:population":0,
    "gn:timezone":"America/Asuncion",
    "iso:country":"PY",
    "name:spa_x_preferred":[
        "Compa\u00f1\u00eda Jhugu\u00e1 Rey"
    ],
    "name:und_x_variant":[
        "Jhugua Rey"
    ],
    "wof:name":"Compania Jhugua Rey",
    "wof:placetype":"locality"
},
  "geometry": {"coordinates":[-56.73621,-24.41214],"type":"Point"}
}