{
  "type": "Feature",
  "properties": {
    "gn:admin1_code":"17.0",
    "gn:admin2_code":"0201",
    "gn:asciiname":"Puerto Ybapobo",
    "gn:cc2":"PY",
    "gn:country_code":"PY",
    "gn:dem":73,
    "gn:feature_class":"P",
    "gn:feature_code":"PPL",
    "gn:name":"Puerto Ybapob\u00f3",
    "gn:population":0,
    "gn:timezone":"America/Asuncion",
    "iso:country":"PY",
    "name:und_x_variant":[
        "Iba-Pobo",
        "Ybapobo",
        "Puerto Iba-pob\u00f3",
        "Puerto Ybapob\u00f3"
    ],
    "wof:name":"Puerto Ybapobo",
    "wof:placetype":"locality"
},
  "geometry": {"coordinates":[-57.39111,-23.6475],"type":"Point"}
}