{
  "type": "Feature",
  "properties": {
    "iso:country":"PY",
    "ne:ADM0CAP":0.0,
    "ne:ADM0NAME":"Paraguay",
    "ne:ADM0_A3":"PRY",
    "ne:ADM1NAME":"Boqueran",
    "ne:ADMIN1_COD":0,
    "ne:CAPALT":0,
    "ne:CHANGED":0,
    "ne:CHECKME":5,
    "ne:COMPARE":0,
    "ne:DIFFASCII":0,
    "ne:ELEVATION":0.0,
    "ne:FEATURECLA":"Admin-1 capital",
    "ne:GEONAMEID":-1,
    "ne:GEONAMESNO":"No GeoNames match due to small population, not in GeoNames, or poor NEV placement.",
    "ne:GN_POP":0,
    "ne:GTOPO30":0.0,
    "ne:ISO_A2":"PY",
    "ne:LABELRANK":7,
    "ne:LATITUDE":-20.51995,
    "ne:LONGITUDE":-62.209986,
    "ne:LS_MATCH":0,
    "ne:LS_NAME":"General Eugenio Alejandrino Garay",
    "ne:MAX_AREAKM":0.0,
    "ne:MAX_AREAMI":0.0,
    "ne:MAX_BBXMAX":0.0,
    "ne:MAX_BBXMIN":0.0,
    "ne:MAX_BBYMAX":0.0,
    "ne:MAX_BBYMIN":0.0,
    "ne:MAX_NATSCA":0.0,
    "ne:MAX_PERKM":0.0,
    "ne:MAX_PERMI":0.0,
    "ne:MAX_POP10":0,
    "ne:MAX_POP20":0,
    "ne:MAX_POP300":0,
    "ne:MAX_POP310":0,
    "ne:MAX_POP50":0,
    "ne:MEAN_BBXC":0.0,
    "ne:MEAN_BBYC":0.0,
    "ne:MEGACITY":0,
    "ne:MIN_AREAKM":0.0,
    "ne:MIN_AREAMI":0.0,
    "ne:MIN_BBXMAX":0.0,
    "ne:MIN_BBXMIN":0.0,
    "ne:MIN_BBYMAX":0.0,
    "ne:MIN_BBYMIN":0.0,
    "ne:MIN_PERKM":0.0,
    "ne:MIN_PERMI":0.0,
    "ne:NAME":"General Eugenio Alejandrino Garay",
    "ne:NAMEALT":"Fortin Coronel Eugenia Garay",
    "ne:NAMEASCII":"General Eugenio Alejandrino Garay",
    "ne:NAMEDIFF":0,
    "ne:NATSCALE":10,
    "ne:POP1950":0,
    "ne:POP1955":0,
    "ne:POP1960":0,
    "ne:POP1965":0,
    "ne:POP1970":0,
    "ne:POP1975":0,
    "ne:POP1980":0,
    "ne:POP1985":0,
    "ne:POP1990":0,
    "ne:POP1995":0,
    "ne:POP2000":0,
    "ne:POP2005":0,
    "ne:POP2010":0,
    "ne:POP2015":0,
    "ne:POP2020":0,
    "ne:POP2025":0,
    "ne:POP2050":0,
    "ne:POP_MAX":972,
    "ne:POP_MIN":972,
    "ne:POP_OTHER":0,
    "ne:RANK_MAX":2,
    "ne:RANK_MIN":2,
    "ne:SCALERANK":8,
    "ne:SOV0NAME":"Paraguay",
    "ne:SOV_A3":"PRY",
    "ne:UN_FID":0,
    "ne:UN_LAT":0.0,
    "ne:UN_LONG":0.0,
    "ne:WORLDCITY":0,
    "ne:min_zoom":7.0,
    "wof:name":"General Eugenio Alejandrino Garay",
    "wof:placetype":"locality"
},
  "geometry": {"coordinates":[-62.20998600426765,-20.51995033893286],"type":"Point"}
}