{
  "type": "Feature",
  "properties": {
    "gn:admin1_code":"24.0",
    "gn:admin2_code":"1602",
    "gn:asciiname":"La Dorada",
    "gn:country_code":"PY",
    "gn:dem":233,
    "gn:feature_class":"P",
    "gn:feature_code":"PPL",
    "gn:name":"La Dorada",
    "gn:population":0,
    "gn:timezone":"America/Asuncion",
    "iso:country":"PY",
    "name:ceb_x_preferred":[
        "La Dorada"
    ],
    "name:mlg_x_preferred":[
        "La Dorada"
    ],
    "name:spa_x_preferred":[
        "La Dorada"
    ],
    "name:srp_x_preferred":[
        "\u041b\u0430 \u0414\u043e\u0440\u0430\u0434\u0430"
    ],
    "name:swe_x_preferred":[
        "La Dorada"
    ],
    "wof:name":"La Dorada",
    "wof:placetype":"locality"
},
  "geometry": {"coordinates":[-62.15,-22.71667],"type":"Point"}
}