{
  "type": "Feature",
  "properties": {
    "gn:admin1_code":"16.0",
    "gn:admin2_code":"1504",
    "gn:asciiname":"Estancia San Jose",
    "gn:country_code":"PY",
    "gn:dem":74,
    "gn:feature_class":"P",
    "gn:feature_code":"PPL",
    "gn:name":"Estancia San Jos\u00e9",
    "gn:population":0,
    "gn:timezone":"America/Asuncion",
    "iso:country":"PY",
    "wof:name":"Estancia San Jose",
    "wof:placetype":"locality"
},
  "geometry": {"coordinates":[-57.6075,-23.75306],"type":"Point"}
}