{
  "type": "Feature",
  "properties": {
    "iso:country":"PY",
    "ne:ADM0CAP":0.0,
    "ne:ADM0NAME":"Paraguay",
    "ne:ADM0_A3":"PRY",
    "ne:ADM1NAME":"Caazapa",
    "ne:ADMIN1_COD":0,
    "ne:CAPALT":0,
    "ne:CHANGED":0,
    "ne:CHECKME":5,
    "ne:COMPARE":0,
    "ne:DIFFASCII":0,
    "ne:ELEVATION":0.0,
    "ne:FEATURECLA":"Admin-1 capital",
    "ne:GEONAMEID":-1,
    "ne:GEONAMESNO":"No GeoNames match due to small population, not in GeoNames, or poor NEV placement.",
    "ne:GN_POP":0,
    "ne:GTOPO30":0.0,
    "ne:ISO_A2":"PY",
    "ne:LABELRANK":7,
    "ne:LATITUDE":-26.200017,
    "ne:LONGITUDE":-56.380006,
    "ne:LS_MATCH":1,
    "ne:LS_NAME":"Caazapa",
    "ne:MAX_AREAKM":5.0,
    "ne:MAX_AREAMI":2.0,
    "ne:MAX_BBXMAX":-56.358333,
    "ne:MAX_BBXMIN":-56.383333,
    "ne:MAX_BBYMAX":-26.183333,
    "ne:MAX_BBYMIN":-26.208333,
    "ne:MAX_NATSCA":10.0,
    "ne:MAX_PERKM":11.0,
    "ne:MAX_PERMI":7.0,
    "ne:MAX_POP10":5504,
    "ne:MAX_POP20":0,
    "ne:MAX_POP300":0,
    "ne:MAX_POP310":0,
    "ne:MAX_POP50":0,
    "ne:MEAN_BBXC":-56.368452,
    "ne:MEAN_BBYC":-26.195833,
    "ne:MEGACITY":0,
    "ne:MIN_AREAKM":5.0,
    "ne:MIN_AREAMI":2.0,
    "ne:MIN_BBXMAX":-56.358333,
    "ne:MIN_BBXMIN":-56.383333,
    "ne:MIN_BBYMAX":-26.183333,
    "ne:MIN_BBYMIN":-26.208333,
    "ne:MIN_PERKM":11.0,
    "ne:MIN_PERMI":7.0,
    "ne:NAME":"Caazapa",
    "ne:NAMEASCII":"Caazapa",
    "ne:NAMEDIFF":0,
    "ne:NATSCALE":10,
    "ne:POP1950":0,
    "ne:POP1955":0,
    "ne:POP1960":0,
    "ne:POP1965":0,
    "ne:POP1970":0,
    "ne:POP1975":0,
    "ne:POP1980":0,
    "ne:POP1985":0,
    "ne:POP1990":0,
    "ne:POP1995":0,
    "ne:POP2000":0,
    "ne:POP2005":0,
    "ne:POP2010":0,
    "ne:POP2015":0,
    "ne:POP2020":0,
    "ne:POP2025":0,
    "ne:POP2050":0,
    "ne:POP_MAX":5504,
    "ne:POP_MIN":5504,
    "ne:POP_OTHER":5504,
    "ne:RANK_MAX":5,
    "ne:RANK_MIN":5,
    "ne:SCALERANK":8,
    "ne:SOV0NAME":"Paraguay",
    "ne:SOV_A3":"PRY",
    "ne:UN_FID":0,
    "ne:UN_LAT":0.0,
    "ne:UN_LONG":0.0,
    "ne:WORLDCITY":0,
    "ne:min_zoom":7.0,
    "wof:name":"Caazapa",
    "wof:placetype":"locality"
},
  "geometry": {"coordinates":[-56.38000594239543,-26.20001707072646],"type":"Point"}
}