{
  "type": "Feature",
  "properties": {
    "gn:admin1_code":"16.0",
    "gn:admin2_code":"1502",
    "gn:asciiname":"Estancia Algarrobo",
    "gn:country_code":"PY",
    "gn:dem":80,
    "gn:feature_class":"P",
    "gn:feature_code":"PPL",
    "gn:name":"Estancia Algarrobo",
    "gn:population":0,
    "gn:timezone":"America/Asuncion",
    "iso:country":"PY",
    "wof:name":"Estancia Algarrobo",
    "wof:placetype":"locality"
},
  "geometry": {"coordinates":[-58.13333000000001,-24.58333],"type":"Point"}
}