{
  "type": "Feature",
  "properties": {
    "gn:admin1_code":"4.0",
    "gn:admin2_code":"0510",
    "gn:asciiname":"Isla Aguaray",
    "gn:country_code":"PY",
    "gn:dem":127,
    "gn:feature_class":"P",
    "gn:feature_code":"PPL",
    "gn:name":"Isla Aguaray",
    "gn:population":0,
    "gn:timezone":"America/Asuncion",
    "iso:country":"PY",
    "wof:name":"Isla Aguaray",
    "wof:placetype":"locality"
},
  "geometry": {"coordinates":[-56.71666999999999,-25.63333],"type":"Point"}
}