{
  "type": "Feature",
  "properties": {
    "gn:admin1_code":"16.0",
    "gn:admin2_code":"1504",
    "gn:asciiname":"Estancia Belen",
    "gn:country_code":"PY",
    "gn:dem":67,
    "gn:feature_class":"P",
    "gn:feature_code":"PPL",
    "gn:name":"Estancia Bel\u00e9n",
    "gn:population":0,
    "gn:timezone":"America/Asuncion",
    "iso:country":"PY",
    "name:spa_x_preferred":[
        "Estancia Bel\u00e9n"
    ],
    "wof:name":"Estancia Belen",
    "wof:placetype":"locality"
},
  "geometry": {"coordinates":[-57.28085,-24.56158],"type":"Point"}
}