{
  "type": "Feature",
  "properties": {
    "gn:admin1_code":"16.0",
    "gn:admin2_code":"1507",
    "gn:asciiname":"Estancia Ceibo",
    "gn:country_code":"PY",
    "gn:dem":122,
    "gn:feature_class":"P",
    "gn:feature_code":"PPL",
    "gn:name":"Estancia Ceibo",
    "gn:population":0,
    "gn:timezone":"America/Asuncion",
    "iso:country":"PY",
    "wof:name":"Estancia Ceibo",
    "wof:placetype":"locality"
},
  "geometry": {"coordinates":[-59.58333,-22.96667],"type":"Point"}
}