{
  "type": "Feature",
  "properties": {
    "gn:admin1_code":"16.0",
    "gn:admin2_code":"1502",
    "gn:asciiname":"Hotel Rio Negro",
    "gn:country_code":"PY",
    "gn:dem":90,
    "gn:feature_class":"P",
    "gn:feature_code":"PPL",
    "gn:name":"Hotel Rio Negro",
    "gn:population":0,
    "gn:timezone":"America/Asuncion",
    "iso:country":"PY",
    "wof:name":"Hotel Rio Negro",
    "wof:placetype":"locality"
},
  "geometry": {"coordinates":[-58.31667,-24.16667],"type":"Point"}
}