{
  "type": "Feature",
  "properties": {
    "gn:admin1_code":"24.0",
    "gn:admin2_code":"1602",
    "gn:asciiname":"Espectro",
    "gn:country_code":"PY",
    "gn:dem":204,
    "gn:feature_class":"P",
    "gn:feature_code":"PPL",
    "gn:name":"Espectro",
    "gn:population":0,
    "gn:timezone":"America/Asuncion",
    "iso:country":"PY",
    "wof:name":"Espectro",
    "wof:placetype":"locality"
},
  "geometry": {"coordinates":[-61.45,-22.48333],"type":"Point"}
}