{
  "type": "Feature",
  "properties": {
    "gn:admin1_code":"17.0",
    "gn:admin2_code":"0220",
    "gn:asciiname":"Estancia San Miguel",
    "gn:country_code":"PY",
    "gn:dem":194,
    "gn:feature_class":"P",
    "gn:feature_code":"PPL",
    "gn:name":"Estancia San Miguel",
    "gn:population":0,
    "gn:timezone":"America/Asuncion",
    "iso:country":"PY",
    "name:spa_x_preferred":[
        "Estancia San Miguel"
    ],
    "wof:name":"Estancia San Miguel",
    "wof:placetype":"locality"
},
  "geometry": {"coordinates":[-56.32481,-24.28921],"type":"Point"}
}