{
  "type": "Feature",
  "properties": {
    "iso:country":"PY",
    "name:ita_x_preferred":[
        "Itap\u00e9"
    ],
    "name:lit_x_preferred":[
        "Itap\u0117"
    ],
    "name:por_x_preferred":[
        "Itap\u00e9"
    ],
    "name:spa_x_preferred":[
        "Itap\u00e9"
    ],
    "name:zho_x_preferred":[
        "\u4f0a\u5854\u4f69"
    ],
    "qs:gn_country":"PY",
    "qs:gn_fcode":"PPL",
    "qs:gn_pop":1641,
    "qs:name":"Itap\u00e9",
    "qs:name_adm0":"Paraguay",
    "qs:name_adm1":"Guair\u00e1",
    "qs:photos":0,
    "qs:photos_1k":0,
    "qs:photos_9k":1,
    "qs:photos_9r":1,
    "qs:photos_all":1,
    "qs:photos_sr":0,
    "qs:placetype":"Town",
    "qs:pop_sr":"3",
    "qs:woe_adm0":23424917,
    "wd:wordcount":16,
    "wof:name":"Itap\u00e9",
    "wof:placetype":"locality",
    "wof:population":1641
},
  "geometry": {"coordinates":[-56.61667,-25.85],"type":"Point"}
}