{
  "type": "Feature",
  "properties": {
    "gn:admin1_code":"6.0",
    "gn:asciiname":"Sant Ana",
    "gn:country_code":"PY",
    "gn:dem":60,
    "gn:feature_class":"P",
    "gn:feature_code":"PPL",
    "gn:name":"Sant Ana",
    "gn:population":0,
    "gn:timezone":"America/Asuncion",
    "iso:country":"PY",
    "wof:name":"Sant Ana",
    "wof:placetype":"locality"
},
  "geometry": {"coordinates":[-57.66016,-25.31664],"type":"Point"}
}