{
  "type": "Feature",
  "properties": {
    "gn:admin1_code":"8.0",
    "gn:admin2_code":"0305",
    "gn:asciiname":"Estancia Lobo Cua",
    "gn:country_code":"PY",
    "gn:dem":83,
    "gn:feature_class":"P",
    "gn:feature_code":"PPL",
    "gn:name":"Estancia Lobo Cu\u00e1",
    "gn:population":0,
    "gn:timezone":"America/Asuncion",
    "iso:country":"PY",
    "name:spa_x_preferred":[
        "Estancia Lobo Cu\u00e1"
    ],
    "name:und_x_variant":[
        "Campo Lobo-cu\u00e9"
    ],
    "wof:name":"Estancia Lobo Cua",
    "wof:placetype":"locality"
},
  "geometry": {"coordinates":[-56.71142,-25.21643],"type":"Point"}
}