{
  "type": "Feature",
  "properties": {
    "gn:admin1_code":"16.0",
    "gn:admin2_code":"1509",
    "gn:asciiname":"Estancia Toldo Cue",
    "gn:country_code":"PY",
    "gn:dem":104,
    "gn:feature_class":"P",
    "gn:feature_code":"PPL",
    "gn:name":"Estancia Toldo Cu\u00e9",
    "gn:population":0,
    "gn:timezone":"America/Asuncion",
    "iso:country":"PY",
    "wof:name":"Estancia Toldo Cue",
    "wof:placetype":"locality"
},
  "geometry": {"coordinates":[-59.16667,-24.55],"type":"Point"}
}