{
  "type": "Feature",
  "properties": {
    "gn:admin1_code":"16.0",
    "gn:admin2_code":"1504",
    "gn:asciiname":"Estancias La Blanca",
    "gn:country_code":"PY",
    "gn:dem":84,
    "gn:feature_class":"P",
    "gn:feature_code":"PPL",
    "gn:name":"Estancias La Blanca",
    "gn:population":0,
    "gn:timezone":"America/Asuncion",
    "iso:country":"PY",
    "wof:name":"Estancias La Blanca",
    "wof:placetype":"locality"
},
  "geometry": {"coordinates":[-58.13333000000001,-23.78333],"type":"Point"}
}