{
  "type": "Feature",
  "properties": {
    "gn:admin1_code":"11.0",
    "gn:admin2_code":"0701",
    "gn:asciiname":"Colonia Rusa",
    "gn:country_code":"PY",
    "gn:dem":154,
    "gn:feature_class":"P",
    "gn:feature_code":"PPL",
    "gn:name":"Colonia Rusa",
    "gn:population":0,
    "gn:timezone":"America/Asuncion",
    "iso:country":"PY",
    "wof:name":"Colonia Rusa",
    "wof:placetype":"locality"
},
  "geometry": {"coordinates":[-55.85,-27.23333],"type":"Point"}
}