{
  "type": "Feature",
  "properties": {
    "gn:admin1_code":"16.0",
    "gn:admin2_code":"1503",
    "gn:asciiname":"Estancia Caceres Cue",
    "gn:country_code":"PY",
    "gn:dem":90,
    "gn:feature_class":"P",
    "gn:feature_code":"PPL",
    "gn:name":"Estancia Caceres Cu\u00e9",
    "gn:population":0,
    "gn:timezone":"America/Asuncion",
    "iso:country":"PY",
    "wof:name":"Estancia Caceres Cue",
    "wof:placetype":"locality"
},
  "geometry": {"coordinates":[-58.23333,-22.98333],"type":"Point"}
}