{
  "type": "Feature",
  "properties": {
    "gn:admin1_code":"11.0",
    "gn:admin2_code":"0707",
    "gn:asciiname":"Asseradero",
    "gn:country_code":"PY",
    "gn:dem":83,
    "gn:feature_class":"P",
    "gn:feature_code":"PPL",
    "gn:name":"Asseradero",
    "gn:population":0,
    "gn:timezone":"America/Asuncion",
    "iso:country":"PY",
    "wof:name":"Asseradero",
    "wof:placetype":"locality"
},
  "geometry": {"coordinates":[-56.16667,-27.21667],"type":"Point"}
}