{
  "type": "Feature",
  "properties": {
    "gn:admin1_code":"16.0",
    "gn:asciiname":"Estancia La Angelica",
    "gn:country_code":"PY",
    "gn:dem":110,
    "gn:feature_class":"P",
    "gn:feature_code":"PPL",
    "gn:name":"Estancia La Angelica",
    "gn:population":0,
    "gn:timezone":"America/Asuncion",
    "iso:country":"PY",
    "wof:name":"Estancia La Angelica",
    "wof:placetype":"locality"
},
  "geometry": {"coordinates":[-59.36666999999999,-24.45],"type":"Point"}
}