{
  "type": "Feature",
  "properties": {
    "iso:country":"PY",
    "name:unk_x_variant":[
        "Puerto Villa del Rosario"
    ],
    "ne:ADM0CAP":0.0,
    "ne:ADM0NAME":"Paraguay",
    "ne:ADM0_A3":"PRY",
    "ne:ADM1NAME":"San Pedro",
    "ne:ADMIN1_COD":17,
    "ne:CAPALT":0,
    "ne:CHANGED":0,
    "ne:CHECKME":0,
    "ne:COMPARE":0,
    "ne:DIFFASCII":0,
    "ne:ELEVATION":0.0,
    "ne:FEATURECLA":"Populated place",
    "ne:FEATURE_CL":"P",
    "ne:FEATURE_CO":"PPL",
    "ne:GEONAMEID":3437342,
    "ne:GEONAMESNO":"GeoNames spatial join with similar names only.",
    "ne:GN_ASCII":"Puerto Rosario",
    "ne:GN_POP":5123,
    "ne:GTOPO30":62.0,
    "ne:ISO_A2":"PY",
    "ne:LABELRANK":7,
    "ne:LATITUDE":-24.419609,
    "ne:LONGITUDE":-57.100014,
    "ne:LS_MATCH":1,
    "ne:LS_NAME":"Rosario3",
    "ne:MAX_AREAKM":2.0,
    "ne:MAX_AREAMI":1.0,
    "ne:MAX_BBXMAX":-57.108333,
    "ne:MAX_BBXMIN":-57.125,
    "ne:MAX_BBYMAX":-24.416667,
    "ne:MAX_BBYMIN":-24.433333,
    "ne:MAX_NATSCA":20.0,
    "ne:MAX_PERKM":7.0,
    "ne:MAX_PERMI":4.0,
    "ne:MAX_POP10":2155,
    "ne:MAX_POP20":2155,
    "ne:MAX_POP300":0,
    "ne:MAX_POP310":0,
    "ne:MAX_POP50":0,
    "ne:MEAN_BBXC":-57.115278,
    "ne:MEAN_BBYC":-24.423611,
    "ne:MEGACITY":0,
    "ne:MIN_AREAKM":2.0,
    "ne:MIN_AREAMI":1.0,
    "ne:MIN_BBXMAX":-57.108333,
    "ne:MIN_BBXMIN":-57.125,
    "ne:MIN_BBYMAX":-24.416667,
    "ne:MIN_BBYMIN":-24.433333,
    "ne:MIN_PERKM":7.0,
    "ne:MIN_PERMI":4.0,
    "ne:NAME":"Rosario",
    "ne:NAMEASCII":"Rosario",
    "ne:NAMEDIFF":0,
    "ne:NATSCALE":20,
    "ne:POP1950":0,
    "ne:POP1955":0,
    "ne:POP1960":0,
    "ne:POP1965":0,
    "ne:POP1970":0,
    "ne:POP1975":0,
    "ne:POP1980":0,
    "ne:POP1985":0,
    "ne:POP1990":0,
    "ne:POP1995":0,
    "ne:POP2000":0,
    "ne:POP2005":0,
    "ne:POP2010":0,
    "ne:POP2015":0,
    "ne:POP2020":0,
    "ne:POP2025":0,
    "ne:POP2050":0,
    "ne:POP_MAX":5123,
    "ne:POP_MIN":2155,
    "ne:POP_OTHER":829226,
    "ne:RANK_MAX":5,
    "ne:RANK_MIN":4,
    "ne:SCALERANK":7,
    "ne:SOV0NAME":"Paraguay",
    "ne:SOV_A3":"PRY",
    "ne:TIMEZONE":"America/Asuncion",
    "ne:UN_FID":0,
    "ne:UN_LAT":0.0,
    "ne:UN_LONG":0.0,
    "ne:WORLDCITY":0,
    "qs:gn_country":"PY",
    "qs:gn_fcode":"PPL",
    "qs:gn_pop":5123,
    "qs:name":"Puerto Rosario",
    "qs:name_adm0":"Paraguay",
    "qs:name_adm1":"San Pedro",
    "qs:photos":0,
    "qs:photos_1k":0,
    "qs:photos_9k":0,
    "qs:photos_9r":0,
    "qs:photos_all":0,
    "qs:photos_sr":0,
    "qs:placetype":"Town",
    "qs:pop_sr":"5",
    "qs:woe_adm0":23424917,
    "wd:wordcount":435,
    "wof:name":"Puerto Rosario",
    "wof:placetype":"locality",
    "wof:population":5123
},
  "geometry": {"coordinates":[-57.08333,-24.45],"type":"Point"}
}