{
  "type": "Feature",
  "properties": {
    "gn:admin1_code":"8.0",
    "gn:admin2_code":"0310",
    "gn:asciiname":"Estancia Molina Cue",
    "gn:country_code":"PY",
    "gn:dem":103,
    "gn:feature_class":"P",
    "gn:feature_code":"PPL",
    "gn:name":"Estancia Molina Cu\u00e9",
    "gn:population":0,
    "gn:timezone":"America/Asuncion",
    "iso:country":"PY",
    "name:spa_x_preferred":[
        "Estancia Molina Cu\u00e9"
    ],
    "wof:name":"Estancia Molina Cue",
    "wof:placetype":"locality"
},
  "geometry": {"coordinates":[-56.60183000000001,-25.06938],"type":"Point"}
}