{
  "type": "Feature",
  "properties": {
    "gn:admin1_code":"8.0",
    "gn:admin2_code":"0307",
    "gn:asciiname":"Colonia Curupayty",
    "gn:country_code":"PY",
    "gn:dem":165,
    "gn:feature_class":"P",
    "gn:feature_code":"PPL",
    "gn:name":"Colonia Curupayty",
    "gn:population":0,
    "gn:timezone":"America/Asuncion",
    "iso:country":"PY",
    "wof:name":"Colonia Curupayty",
    "wof:placetype":"locality"
},
  "geometry": {"coordinates":[-56.98333,-25.41667],"type":"Point"}
}