{
  "type": "Feature",
  "properties": {
    "gn:admin1_code":"16.0",
    "gn:asciiname":"Estancia San Blas",
    "gn:country_code":"PY",
    "gn:dem":114,
    "gn:feature_class":"P",
    "gn:feature_code":"PPL",
    "gn:name":"Estancia San Blas",
    "gn:population":0,
    "gn:timezone":"America/Asuncion",
    "iso:country":"PY",
    "wof:name":"Estancia San Blas",
    "wof:placetype":"locality"
},
  "geometry": {"coordinates":[-59.51667,-24.33333],"type":"Point"}
}