{
  "type": "Feature",
  "properties": {
    "iso:country":"PY",
    "name:deu_x_preferred":[
        "General Artigas"
    ],
    "name:ita_x_preferred":[
        "General Artigas"
    ],
    "name:por_x_preferred":[
        "General Artigas"
    ],
    "name:spa_x_preferred":[
        "General Artigas"
    ],
    "name:unk_x_variant":[
        "Bobi-Cang\u00f3"
    ],
    "name:zho_x_preferred":[
        "\u963f\u723e\u8482\u52a0\u65af\u5c07\u8ecd\u93ae"
    ],
    "qs:gn_country":"PY",
    "qs:gn_fcode":"PPL",
    "qs:gn_pop":4073,
    "qs:name":"General Artigas",
    "qs:name_adm0":"Paraguay",
    "qs:name_adm1":"Itap\u00faa",
    "qs:photos":0,
    "qs:photos_1k":0,
    "qs:photos_9k":1,
    "qs:photos_9r":1,
    "qs:photos_all":21,
    "qs:photos_sr":0,
    "qs:placetype":"Town",
    "qs:pop_sr":"4",
    "qs:woe_adm0":23424917,
    "wd:wordcount":39,
    "wof:name":"General Artigas",
    "wof:placetype":"locality",
    "wof:population":4073
},
  "geometry": {"coordinates":[-56.21667,-26.93333],"type":"Point"}
}