{
  "type": "Feature",
  "properties": {
    "gn:admin1_code":"15.0",
    "gn:admin2_code":"0913",
    "gn:asciiname":"Colonia Carlos A. Lopez",
    "gn:country_code":"PY",
    "gn:dem":264,
    "gn:feature_class":"P",
    "gn:feature_code":"PPLL",
    "gn:name":"Colonia Carlos A. L\u00f3pez",
    "gn:population":0,
    "gn:timezone":"America/Asuncion",
    "iso:country":"PY",
    "name:spa_x_preferred":[
        "Colonia Carlos A. L\u00f3pez"
    ],
    "wof:name":"Colonia Carlos A. Lopez",
    "wof:placetype":"locality"
},
  "geometry": {"coordinates":[-56.95411,-25.72021],"type":"Point"}
}