{
  "type": "Feature",
  "properties": {
    "gn:admin1_code":"16.0",
    "gn:admin2_code":"1509",
    "gn:asciiname":"Estancia La Esperanza",
    "gn:country_code":"PY",
    "gn:dem":99,
    "gn:feature_class":"P",
    "gn:feature_code":"PPL",
    "gn:name":"Estancia La Esperanza",
    "gn:population":0,
    "gn:timezone":"America/Asuncion",
    "iso:country":"PY",
    "wof:name":"Estancia La Esperanza",
    "wof:placetype":"locality"
},
  "geometry": {"coordinates":[-59.01667,-24.53333],"type":"Point"}
}