{
  "type": "Feature",
  "properties": {
    "gn:admin1_code":"13.0",
    "gn:admin2_code":"1209",
    "gn:asciiname":"Compania Potrero Esteche",
    "gn:country_code":"PY",
    "gn:dem":72,
    "gn:feature_class":"P",
    "gn:feature_code":"PPL",
    "gn:name":"Compa\u00f1\u00eda Potrero Esteche",
    "gn:population":0,
    "gn:timezone":"America/Asuncion",
    "iso:country":"PY",
    "name:spa_x_preferred":[
        "Compa\u00f1\u00eda Potrero Esteche"
    ],
    "name:und_x_variant":[
        "Potrero Esteche"
    ],
    "wof:name":"Compania Potrero Esteche",
    "wof:placetype":"locality"
},
  "geometry": {"coordinates":[-57.66392,-27.12211],"type":"Point"}
}