{
  "type": "Feature",
  "properties": {
    "gn:admin1_code":"16.0",
    "gn:admin2_code":"1504",
    "gn:asciiname":"Puesto Alegre",
    "gn:country_code":"PY",
    "gn:dem":70,
    "gn:feature_class":"P",
    "gn:feature_code":"PPL",
    "gn:name":"Puesto Alegre",
    "gn:population":0,
    "gn:timezone":"America/Asuncion",
    "iso:country":"PY",
    "wof:name":"Puesto Alegre",
    "wof:placetype":"locality"
},
  "geometry": {"coordinates":[-57.43333000000001,-23.76667],"type":"Point"}
}