{
  "type": "Feature",
  "properties": {
    "gn:admin1_code":"7.0",
    "gn:admin2_code":"0101",
    "gn:asciiname":"Estancia San Antonio",
    "gn:cc2":"PY",
    "gn:country_code":"PY",
    "gn:dem":114,
    "gn:feature_class":"P",
    "gn:feature_code":"PPL",
    "gn:name":"Estancia San Antonio",
    "gn:population":0,
    "gn:timezone":"America/Asuncion",
    "iso:country":"PY",
    "name:und_x_variant":[
        "San Antonio",
        "Estancia San Antonio"
    ],
    "wof:name":"Estancia San Antonio",
    "wof:placetype":"locality"
},
  "geometry": {"coordinates":[-56.86666999999999,-23.01667],"type":"Point"}
}