{
  "type": "Feature",
  "properties": {
    "gn:admin1_code":"23.0",
    "gn:admin2_code":"1704",
    "gn:asciiname":"Campos",
    "gn:cc2":"PY",
    "gn:country_code":"PY",
    "gn:dem":119,
    "gn:feature_class":"P",
    "gn:feature_code":"PPL",
    "gn:name":"Campos",
    "gn:population":0,
    "gn:timezone":"America/Asuncion",
    "iso:country":"PY",
    "name:und_x_variant":[
        "Fortin Campos",
        "Campos"
    ],
    "wof:name":"Campos",
    "wof:placetype":"locality"
},
  "geometry": {"coordinates":[-59.53333000000001,-20.13333],"type":"Point"}
}