{
  "type": "Feature",
  "properties": {
    "iso:country":"PY",
    "name:ara_x_preferred":[
        "\u0646\u0627\u0646\u0627\u0648\u0627"
    ],
    "name:ben_x_preferred":[
        "\u09a8\u09be\u09a8\u09be\u0993\u09af\u09bc\u09be"
    ],
    "name:dan_x_preferred":[
        "Nanawa"
    ],
    "name:ell_x_preferred":[
        "\u039d\u03b1\u03bd\u03ac\u03b2\u03b1"
    ],
    "name:eng_x_preferred":[
        "Nanawa"
    ],
    "name:eus_x_preferred":[
        "Nanawa"
    ],
    "name:fin_x_preferred":[
        "Nanawa"
    ],
    "name:fra_x_preferred":[
        "Nanawa"
    ],
    "name:grn_x_preferred":[
        "Nanawa"
    ],
    "name:guj_x_preferred":[
        "\u0aa8\u0abe\u0aa8\u0ab5\u0abe"
    ],
    "name:hin_x_preferred":[
        "\u0928\u093e\u0928\u093e\u0935\u093e"
    ],
    "name:ind_x_preferred":[
        "Nanawa"
    ],
    "name:ita_x_preferred":[
        "Nanawa"
    ],
    "name:jpn_x_preferred":[
        "\u30ca\u30ca\u30ef"
    ],
    "name:kan_x_preferred":[
        "\u0ca8\u0cbe\u0ca8\u0cbe\u0cb5\u0cbe"
    ],
    "name:kor_x_preferred":[
        "\ub098\ub098\uc640"
    ],
    "name:lav_x_preferred":[
        "Nanava"
    ],
    "name:lit_x_preferred":[
        "Nanava"
    ],
    "name:mar_x_preferred":[
        "\u0928\u093e\u0928\u093e\u0935\u093e"
    ],
    "name:msa_x_preferred":[
        "Nanawa"
    ],
    "name:nld_x_preferred":[
        "Nanawa"
    ],
    "name:nob_x_preferred":[
        "Nanawa"
    ],
    "name:pol_x_preferred":[
        "Nanawa"
    ],
    "name:por_x_preferred":[
        "Nanawa"
    ],
    "name:rus_x_preferred":[
        "\u041d\u0430\u043d\u0430\u0432\u0430"
    ],
    "name:sin_x_preferred":[
        "\u0db1\u0db1\u0dc0\u0dcf"
    ],
    "name:spa_x_preferred":[
        "Nanawa"
    ],
    "name:swe_x_preferred":[
        "Nanawa"
    ],
    "name:tam_x_preferred":[
        "\u0ba8\u0ba9\u0bb5\u0bbe"
    ],
    "name:tel_x_preferred":[
        "\u0c28\u0c3e\u0c28\u0c3e\u0c35\u0c3e"
    ],
    "name:tha_x_preferred":[
        "\u0e19\u0e32\u0e01\u0e32\u0e27\u0e32"
    ],
    "name:tur_x_preferred":[
        "Nanawa"
    ],
    "name:ukr_x_preferred":[
        "\u041d\u0430\u043d\u0430\u0432\u0430"
    ],
    "name:urd_x_preferred":[
        "\u0646\u0627\u0646\u0627\u0648\u0627"
    ],
    "name:vie_x_preferred":[
        "Nanawa"
    ],
    "name:zho_x_preferred":[
        "\u7d0d\u7d0d\u74e6"
    ],
    "qs:gn_country":"PY",
    "qs:gn_fcode":"PPL",
    "qs:gn_pop":5587,
    "qs:name":"Nanawa",
    "qs:name_adm0":"Paraguay",
    "qs:name_adm1":"Presidente Hayes",
    "qs:photos":1196,
    "qs:photos_1k":242,
    "qs:photos_9k":5,
    "qs:photos_9r":7,
    "qs:photos_all":1196,
    "qs:photos_sr":11,
    "qs:placetype":"Town",
    "qs:pop_sr":"5",
    "qs:woe_adm0":23424917,
    "wof:name":"Nanawa",
    "wof:placetype":"locality",
    "wof:population":5587
},
  "geometry": {"coordinates":[-57.66667,-25.26667],"type":"Point"}
}