{
  "type": "Feature",
  "properties": {
    "iso:country":"PY",
    "name:grn_x_preferred":[
        "Nanawa"
    ],
    "name:ita_x_preferred":[
        "Nanawa"
    ],
    "name:pol_x_preferred":[
        "Nanawa"
    ],
    "name:por_x_preferred":[
        "Nanawa"
    ],
    "name:spa_x_preferred":[
        "Nanawa"
    ],
    "name:ukr_x_preferred":[
        "\u041d\u0430\u043d\u0430\u0432\u0430"
    ],
    "name:zho_x_preferred":[
        "\u7d0d\u7d0d\u74e6"
    ],
    "qs:gn_country":"PY",
    "qs:gn_fcode":"PPL",
    "qs:gn_pop":5587,
    "qs:name":"Nanawa",
    "qs:name_adm0":"Paraguay",
    "qs:name_adm1":"Presidente Hayes",
    "qs:photos":1196,
    "qs:photos_1k":242,
    "qs:photos_9k":5,
    "qs:photos_9r":7,
    "qs:photos_all":1196,
    "qs:photos_sr":11,
    "qs:placetype":"Town",
    "qs:pop_sr":"5",
    "qs:woe_adm0":23424917,
    "wof:name":"Nanawa",
    "wof:placetype":"locality",
    "wof:population":5587
},
  "geometry": {"coordinates":[-57.66667,-25.26667],"type":"Point"}
}