{
  "type": "Feature",
  "properties": {
    "gn:admin1_code":"16.0",
    "gn:admin2_code":"1504",
    "gn:asciiname":"Estancia Jose Dolores Genes",
    "gn:country_code":"PY",
    "gn:dem":65,
    "gn:feature_class":"P",
    "gn:feature_code":"PPL",
    "gn:name":"Estancia Jos\u00e9 Dolores Genes",
    "gn:population":0,
    "gn:timezone":"America/Asuncion",
    "iso:country":"PY",
    "wof:name":"Estancia Jose Dolores Genes",
    "wof:placetype":"locality"
},
  "geometry": {"coordinates":[-57.63333000000001,-25.23333],"type":"Point"}
}