{
  "type": "Feature",
  "properties": {
    "gn:admin1_code":"7.0",
    "gn:admin2_code":"0101",
    "gn:asciiname":"Toldo Cue",
    "gn:cc2":"PY",
    "gn:country_code":"PY",
    "gn:dem":98,
    "gn:feature_class":"P",
    "gn:feature_code":"PPL",
    "gn:name":"Toldo Cu\u00e9",
    "gn:population":0,
    "gn:timezone":"America/Asuncion",
    "iso:country":"PY",
    "name:und_x_variant":[
        "Estancia Toldo-cu\u00e9",
        "Toldo Cu\u00e9"
    ],
    "wof:name":"Toldo Cue",
    "wof:placetype":"locality"
},
  "geometry": {"coordinates":[-57.41667,-23.23333],"type":"Point"}
}