{
  "type": "Feature",
  "properties": {
    "gn:admin1_code":"7.0",
    "gn:admin2_code":"0101",
    "gn:asciiname":"Puerto Napegue",
    "gn:country_code":"PY",
    "gn:dem":64,
    "gn:feature_class":"P",
    "gn:feature_code":"PPL",
    "gn:name":"Puerto Napegu\u00e9",
    "gn:population":0,
    "gn:timezone":"America/Asuncion",
    "iso:country":"PY",
    "wof:name":"Puerto Napegue",
    "wof:placetype":"locality"
},
  "geometry": {"coordinates":[-57.66667,-23.06667],"type":"Point"}
}