{
  "type": "Feature",
  "properties": {
    "gn:admin1_code":"11.0",
    "gn:admin2_code":"0712",
    "gn:asciiname":"Estancia Ramon Davalos",
    "gn:country_code":"PY",
    "gn:dem":86,
    "gn:feature_class":"P",
    "gn:feature_code":"PPLL",
    "gn:name":"Estancia Ram\u00f3n D\u00e1valos",
    "gn:population":0,
    "gn:timezone":"America/Asuncion",
    "iso:country":"PY",
    "name:spa_x_preferred":[
        "Estancia Ram\u00f3n D\u00e1valos"
    ],
    "wof:name":"Estancia Ramon Davalos",
    "wof:placetype":"locality"
},
  "geometry": {"coordinates":[-56.43395,-27.03741],"type":"Point"}
}