{
  "type": "Feature",
  "properties": {
    "gn:admin1_code":"8.0",
    "gn:admin2_code":"0320",
    "gn:asciiname":"Estancia Nandypay",
    "gn:country_code":"PY",
    "gn:dem":74,
    "gn:feature_class":"P",
    "gn:feature_code":"PPL",
    "gn:name":"Estancia Nandyp\u00e1y",
    "gn:population":0,
    "gn:timezone":"America/Asuncion",
    "iso:country":"PY",
    "name:spa_x_preferred":[
        "Estancia Nandyp\u00e1y"
    ],
    "wof:name":"Estancia Nandypay",
    "wof:placetype":"locality"
},
  "geometry": {"coordinates":[-56.80715,-25.09266],"type":"Point"}
}