{
  "type": "Feature",
  "properties": {
    "gn:admin1_code":"12.0",
    "gn:admin2_code":"0807",
    "gn:asciiname":"Curupayty",
    "gn:country_code":"PY",
    "gn:dem":113,
    "gn:feature_class":"P",
    "gn:feature_code":"PPL",
    "gn:name":"Curupayty",
    "gn:population":0,
    "gn:timezone":"America/Asuncion",
    "iso:country":"PY",
    "wof:name":"Curupayty",
    "wof:placetype":"locality"
},
  "geometry": {"coordinates":[-56.78333000000001,-26.85],"type":"Point"}
}