{
  "type": "Feature",
  "properties": {
    "gn:admin1_code":"24.0",
    "gn:admin2_code":"1602",
    "gn:asciiname":"Establecimiento Mil",
    "gn:country_code":"PY",
    "gn:dem":241,
    "gn:feature_class":"P",
    "gn:feature_code":"PPL",
    "gn:name":"Establecimiento Mil",
    "gn:population":0,
    "gn:timezone":"America/Asuncion",
    "iso:country":"PY",
    "wof:name":"Establecimiento Mil",
    "wof:placetype":"locality"
},
  "geometry": {"coordinates":[-62.26667,-22.36667000000001],"type":"Point"}
}