{
  "type": "Feature",
  "properties": {
    "gn:admin1_code":"7.0",
    "gn:admin2_code":"0109",
    "gn:asciiname":"Estancia Santa Luisa",
    "gn:cc2":"PY",
    "gn:country_code":"PY",
    "gn:dem":186,
    "gn:feature_class":"P",
    "gn:feature_code":"PPL",
    "gn:name":"Estancia Santa Luisa",
    "gn:population":0,
    "gn:timezone":"America/Asuncion",
    "iso:country":"PY",
    "name:und_x_variant":[
        "Santa Luisa",
        "Estancia Santa Luisa"
    ],
    "wof:name":"Estancia Santa Luisa",
    "wof:placetype":"locality"
},
  "geometry": {"coordinates":[-56.76667,-22.43333],"type":"Point"}
}