{
  "type": "Feature",
  "properties": {
    "gn:admin1_code":"8.0",
    "gn:admin2_code":"0312",
    "gn:asciiname":"Estancia Kennedy",
    "gn:country_code":"PY",
    "gn:dem":99,
    "gn:feature_class":"P",
    "gn:feature_code":"PPL",
    "gn:name":"Estancia Kennedy",
    "gn:population":0,
    "gn:timezone":"America/Asuncion",
    "iso:country":"PY",
    "name:spa_x_preferred":[
        "Estancia Kennedy"
    ],
    "wof:name":"Estancia Kennedy",
    "wof:placetype":"locality"
},
  "geometry": {"coordinates":[-56.73165,-25.30445],"type":"Point"}
}