{
  "type": "Feature",
  "properties": {
    "gn:admin1_code":"12.0",
    "gn:admin2_code":"0808",
    "gn:asciiname":"Estancia San Juan",
    "gn:country_code":"PY",
    "gn:dem":96,
    "gn:feature_class":"P",
    "gn:feature_code":"PPL",
    "gn:name":"Estancia San Juan",
    "gn:population":0,
    "gn:timezone":"America/Asuncion",
    "iso:country":"PY",
    "name:spa_x_preferred":[
        "Estancia San Juan"
    ],
    "wof:name":"Estancia San Juan",
    "wof:placetype":"locality"
},
  "geometry": {"coordinates":[-56.67838,-27.15639],"type":"Point"}
}