{
  "type": "Feature",
  "properties": {
    "gn:admin1_code":"5.0",
    "gn:admin2_code":"0608",
    "gn:asciiname":"Tavai",
    "gn:cc2":"PY",
    "gn:country_code":"PY",
    "gn:dem":266,
    "gn:feature_class":"P",
    "gn:feature_code":"PPL",
    "gn:name":"Tava\u00ed",
    "gn:population":0,
    "gn:timezone":"America/Asuncion",
    "iso:country":"PY",
    "name:und_x_variant":[
        "Tabai",
        "Tava\u00ed"
    ],
    "wof:name":"Tavai",
    "wof:placetype":"locality"
},
  "geometry": {"coordinates":[-55.53333000000001,-26.11667000000001],"type":"Point"}
}