{
  "type": "Feature",
  "properties": {
    "gn:admin1_code":"12.0",
    "gn:admin2_code":"0808",
    "gn:asciiname":"Puesto Lomita",
    "gn:country_code":"PY",
    "gn:dem":82,
    "gn:feature_class":"P",
    "gn:feature_code":"PPL",
    "gn:name":"Puesto Lomita",
    "gn:population":0,
    "gn:timezone":"America/Asuncion",
    "iso:country":"PY",
    "name:spa_x_preferred":[
        "Puesto Lomita"
    ],
    "name:und_x_variant":[
        "Lomita"
    ],
    "wof:name":"Puesto Lomita",
    "wof:placetype":"locality"
},
  "geometry": {"coordinates":[-56.9012,-27.18397],"type":"Point"}
}