{
  "type": "Feature",
  "properties": {
    "gn:admin1_code":"16.0",
    "gn:admin2_code":"1502",
    "gn:asciiname":"Cana de Castilla",
    "gn:country_code":"PY",
    "gn:dem":90,
    "gn:feature_class":"P",
    "gn:feature_code":"PPL",
    "gn:name":"Ca\u00f1a de Castilla",
    "gn:population":0,
    "gn:timezone":"America/Asuncion",
    "iso:country":"PY",
    "wof:name":"Cana de Castilla",
    "wof:placetype":"locality"
},
  "geometry": {"coordinates":[-58.28333000000001,-24.18333],"type":"Point"}
}