{
  "type": "Feature",
  "properties": {
    "gn:admin1_code":"24.0",
    "gn:admin2_code":"1602",
    "gn:asciiname":"Estancia San Isidro",
    "gn:country_code":"PY",
    "gn:dem":184,
    "gn:feature_class":"P",
    "gn:feature_code":"PPL",
    "gn:name":"Estancia San Isidro",
    "gn:population":0,
    "gn:timezone":"America/Asuncion",
    "iso:country":"PY",
    "wof:name":"Estancia San Isidro",
    "wof:placetype":"locality"
},
  "geometry": {"coordinates":[-61.00861,-21.24778],"type":"Point"}
}