{
  "type": "Feature",
  "properties": {
    "gn:admin1_code":"16.0",
    "gn:asciiname":"Loma",
    "gn:cc2":"PY",
    "gn:country_code":"PY",
    "gn:dem":65,
    "gn:feature_class":"P",
    "gn:feature_code":"PPL",
    "gn:name":"Loma",
    "gn:population":0,
    "gn:timezone":"America/Asuncion",
    "iso:country":"PY",
    "name:und_x_variant":[
        "Puerto Loma",
        "Puerto Lomas",
        "Loma"
    ],
    "wof:name":"Loma",
    "wof:placetype":"locality"
},
  "geometry": {"coordinates":[-57.11666999999999,-24.65],"type":"Point"}
}