{
  "type": "Feature",
  "properties": {
    "gn:admin1_code":"24.0",
    "gn:admin2_code":"1602",
    "gn:asciiname":"Pozo Verde",
    "gn:country_code":"PY",
    "gn:dem":204,
    "gn:feature_class":"P",
    "gn:feature_code":"PPL",
    "gn:name":"Pozo Verde",
    "gn:population":0,
    "gn:timezone":"America/Asuncion",
    "iso:country":"PY",
    "wof:name":"Pozo Verde",
    "wof:placetype":"locality"
},
  "geometry": {"coordinates":[-61.36666999999999,-22.25],"type":"Point"}
}