{
  "type": "Feature",
  "properties": {
    "gn:admin1_code":"23.0",
    "gn:admin2_code":"1701",
    "gn:asciiname":"Campamento Mercedita",
    "gn:cc2":"PY",
    "gn:country_code":"PY",
    "gn:dem":89,
    "gn:feature_class":"P",
    "gn:feature_code":"PPL",
    "gn:name":"Campamento Mercedita",
    "gn:population":0,
    "gn:timezone":"America/Asuncion",
    "iso:country":"PY",
    "name:und_x_variant":[
        "Campamento Santa Mercedita",
        "Campamento Mercedita"
    ],
    "wof:name":"Campamento Mercedita",
    "wof:placetype":"locality"
},
  "geometry": {"coordinates":[-58.56667,-20.41667],"type":"Point"}
}