{
  "type": "Feature",
  "properties": {
    "gn:admin1_code":"23.0",
    "gn:admin2_code":"1701",
    "gn:asciiname":"Puerto Lidia",
    "gn:country_code":"PY",
    "gn:dem":88,
    "gn:feature_class":"P",
    "gn:feature_code":"PPL",
    "gn:name":"Puerto Lidia",
    "gn:population":0,
    "gn:timezone":"America/Asuncion",
    "iso:country":"PY",
    "wof:name":"Puerto Lidia",
    "wof:placetype":"locality"
},
  "geometry": {"coordinates":[-57.96666999999999,-20.96667],"type":"Point"}
}