{
  "type": "Feature",
  "properties": {
    "gn:admin1_code":"16.0",
    "gn:admin2_code":"1507",
    "gn:asciiname":"Estancia Sombrero Jhovy",
    "gn:country_code":"PY",
    "gn:dem":143,
    "gn:feature_class":"P",
    "gn:feature_code":"PPL",
    "gn:name":"Estancia Sombrero Jhovy",
    "gn:population":0,
    "gn:timezone":"America/Asuncion",
    "iso:country":"PY",
    "name:spa_x_preferred":[
        "Estancia Sombrero Jhovy"
    ],
    "wof:name":"Estancia Sombrero Jhovy",
    "wof:placetype":"locality"
},
  "geometry": {"coordinates":[-60.37167,-23.62482],"type":"Point"}
}