{
  "type": "Feature",
  "properties": {
    "gn:admin1_code":"7.0",
    "gn:admin2_code":"0105",
    "gn:asciiname":"Estancia Loma Pora",
    "gn:country_code":"PY",
    "gn:dem":323,
    "gn:feature_class":"P",
    "gn:feature_code":"PPL",
    "gn:name":"Estancia Loma Por\u00e1",
    "gn:population":0,
    "gn:timezone":"America/Asuncion",
    "iso:country":"PY",
    "wof:name":"Estancia Loma Pora",
    "wof:placetype":"locality"
},
  "geometry": {"coordinates":[-57.38333000000001,-22.55],"type":"Point"}
}