{
  "type": "Feature",
  "properties": {
    "gn:admin1_code":"11.0",
    "gn:admin2_code":"0708",
    "gn:asciiname":"Compania Resquin-Cue",
    "gn:country_code":"PY",
    "gn:dem":102,
    "gn:feature_class":"P",
    "gn:feature_code":"PPL",
    "gn:name":"Compa\u00f1\u00eda Resqu\u00edn-Cu\u00e9",
    "gn:population":0,
    "gn:timezone":"America/Asuncion",
    "iso:country":"PY",
    "name:spa_x_preferred":[
        "Compa\u00f1\u00eda Resqu\u00edn-Cu\u00e9"
    ],
    "name:und_x_variant":[
        "Compa\u00f1\u00eda Resqu\u00edn Cu\u00e9"
    ],
    "wof:name":"Compania Resquin-Cue",
    "wof:placetype":"locality"
},
  "geometry": {"coordinates":[-56.23611,-27.25823],"type":"Point"}
}