{
  "type": "Feature",
  "properties": {
    "gn:admin1_code":"12.0",
    "gn:admin2_code":"0802",
    "gn:asciiname":"Estancia Santa Clara",
    "gn:country_code":"PY",
    "gn:dem":76,
    "gn:feature_class":"P",
    "gn:feature_code":"PPL",
    "gn:name":"Estancia Santa Clara",
    "gn:population":0,
    "gn:timezone":"America/Asuncion",
    "iso:country":"PY",
    "name:spa_x_preferred":[
        "Estancia Santa Clara"
    ],
    "wof:name":"Estancia Santa Clara",
    "wof:placetype":"locality"
},
  "geometry": {"coordinates":[-56.85748,-27.37227],"type":"Point"}
}