{
  "type": "Feature",
  "properties": {
    "gn:admin1_code":"1.0",
    "gn:admin2_code":"1020",
    "gn:asciiname":"Guido Coronel",
    "gn:country_code":"PY",
    "gn:dem":327,
    "gn:feature_class":"P",
    "gn:feature_code":"PPL",
    "gn:name":"Guido Coronel",
    "gn:population":0,
    "gn:timezone":"America/Asuncion",
    "iso:country":"PY",
    "name:spa_x_preferred":[
        "Guido Coronel"
    ],
    "name:und_x_variant":[
        "Colonia Padre Guido Coronel"
    ],
    "wof:name":"Guido Coronel",
    "wof:placetype":"locality"
},
  "geometry": {"coordinates":[-54.70306,-25.22245],"type":"Point"}
}