{
  "type": "Feature",
  "properties": {
    "gn:admin1_code":"19.0",
    "gn:admin2_code":"1402",
    "gn:asciiname":"Corpus Christi Viejo",
    "gn:country_code":"PY",
    "gn:dem":397,
    "gn:feature_class":"P",
    "gn:feature_code":"PPL",
    "gn:name":"Corpus Christi Viejo",
    "gn:population":0,
    "gn:timezone":"America/Asuncion",
    "iso:country":"PY",
    "name:spa_x_preferred":[
        "Corpus Christi Viejo"
    ],
    "name:und_x_variant":[
        "Corpus Cristi Viejo"
    ],
    "wof:name":"Corpus Christi Viejo",
    "wof:placetype":"locality"
},
  "geometry": {"coordinates":[-54.95418000000001,-24.09491],"type":"Point"}
}