{
  "type": "Feature",
  "properties": {
    "gn:admin1_code":"16.0",
    "gn:asciiname":"Puerto Cooper",
    "gn:cc2":"PY",
    "gn:country_code":"PY",
    "gn:dem":79,
    "gn:feature_class":"P",
    "gn:feature_code":"PPL",
    "gn:name":"Puerto Cooper",
    "gn:population":0,
    "gn:timezone":"America/Asuncion",
    "iso:country":"PY",
    "name:und_x_variant":[
        "Cooper",
        "Puerto Cooper"
    ],
    "wof:name":"Puerto Cooper",
    "wof:placetype":"locality"
},
  "geometry": {"coordinates":[-57.71666999999999,-23.05],"type":"Point"}
}