{
  "type": "Feature",
  "properties": {
    "gn:admin1_code":"24.0",
    "gn:admin2_code":"1602",
    "gn:asciiname":"Pozo Charata",
    "gn:country_code":"PY",
    "gn:dem":203,
    "gn:feature_class":"P",
    "gn:feature_code":"PPL",
    "gn:name":"Pozo Charata",
    "gn:population":0,
    "gn:timezone":"America/Asuncion",
    "iso:country":"PY",
    "wof:name":"Pozo Charata",
    "wof:placetype":"locality"
},
  "geometry": {"coordinates":[-61.35,-22.26667],"type":"Point"}
}