{
  "type": "Feature",
  "properties": {
    "gn:admin1_code":"16.0",
    "gn:admin2_code":"1507",
    "gn:asciiname":"Estancia Palo Santo",
    "gn:country_code":"PY",
    "gn:dem":116,
    "gn:feature_class":"P",
    "gn:feature_code":"PPL",
    "gn:name":"Estancia Palo Santo",
    "gn:population":0,
    "gn:timezone":"America/Asuncion",
    "iso:country":"PY",
    "wof:name":"Estancia Palo Santo",
    "wof:placetype":"locality"
},
  "geometry": {"coordinates":[-59.28333000000001,-22.16667],"type":"Point"}
}