{
  "type": "Feature",
  "properties": {
    "gn:admin1_code":"1.0",
    "gn:admin2_code":"1015",
    "gn:asciiname":"Curupayty",
    "gn:country_code":"PY",
    "gn:dem":249,
    "gn:feature_class":"P",
    "gn:feature_code":"PPL",
    "gn:name":"Curupayty",
    "gn:population":0,
    "gn:timezone":"America/Asuncion",
    "iso:country":"PY",
    "wof:name":"Curupayty",
    "wof:placetype":"locality"
},
  "geometry": {"coordinates":[-54.96666999999999,-25.81667],"type":"Point"}
}