{
  "type": "Feature",
  "properties": {
    "gn:admin1_code":"23.0",
    "gn:admin2_code":"1701",
    "gn:asciiname":"Estancia Gomez",
    "gn:country_code":"PY",
    "gn:dem":97,
    "gn:feature_class":"P",
    "gn:feature_code":"PPL",
    "gn:name":"Estancia G\u00f3mez",
    "gn:population":0,
    "gn:timezone":"America/Asuncion",
    "iso:country":"PY",
    "wof:name":"Estancia Gomez",
    "wof:placetype":"locality"
},
  "geometry": {"coordinates":[-58.78333000000001,-20.55],"type":"Point"}
}