{
  "type": "Feature",
  "properties": {
    "gn:admin1_code":"23.0",
    "gn:admin2_code":"1701",
    "gn:asciiname":"Puerto Nuevo",
    "gn:country_code":"PY",
    "gn:dem":85,
    "gn:feature_class":"P",
    "gn:feature_code":"PPL",
    "gn:name":"Puerto Nuevo",
    "gn:population":0,
    "gn:timezone":"America/Asuncion",
    "iso:country":"PY",
    "name:ceb_x_preferred":[
        "Puerto Nuevo"
    ],
    "name:deu_x_preferred":[
        "Puerto Nuevo"
    ],
    "name:spa_x_preferred":[
        "Puerto Nuevo"
    ],
    "name:srp_x_preferred":[
        "\u041f\u0443\u0435\u0440\u0442\u043e \u041d\u0443\u0435\u0432\u043e"
    ],
    "name:swe_x_preferred":[
        "Puerto Nuevo"
    ],
    "wof:name":"Puerto Nuevo",
    "wof:placetype":"locality"
},
  "geometry": {"coordinates":[-58.05,-20.61667000000001],"type":"Point"}
}