{
  "type": "Feature",
  "properties": {
    "gn:admin1_code":"16.0",
    "gn:admin2_code":"1504",
    "gn:asciiname":"Estancia Santa Catalina",
    "gn:country_code":"PY",
    "gn:dem":69,
    "gn:feature_class":"P",
    "gn:feature_code":"PPL",
    "gn:name":"Estancia Santa Catalina",
    "gn:population":0,
    "gn:timezone":"America/Asuncion",
    "iso:country":"PY",
    "name:spa_x_preferred":[
        "Estancia Santa Catalina"
    ],
    "wof:name":"Estancia Santa Catalina",
    "wof:placetype":"locality"
},
  "geometry": {"coordinates":[-57.32169,-24.29985],"type":"Point"}
}