{
  "type": "Feature",
  "properties": {
    "gn:admin1_code":"15.0",
    "gn:admin2_code":"0906",
    "gn:asciiname":"Estancia la Abelenda",
    "gn:country_code":"PY",
    "gn:dem":112,
    "gn:feature_class":"P",
    "gn:feature_code":"PPL",
    "gn:name":"Estancia la Abelenda",
    "gn:population":0,
    "gn:timezone":"America/Asuncion",
    "iso:country":"PY",
    "name:spa_x_preferred":[
        "Estancia la Abelenda"
    ],
    "name:und_x_variant":[
        "Estancia La Abelenda"
    ],
    "wof:name":"Estancia la Abelenda",
    "wof:placetype":"locality"
},
  "geometry": {"coordinates":[-57.08111,-25.69523],"type":"Point"}
}