{
  "type": "Feature",
  "properties": {
    "iso:country":"PY",
    "name:bul_x_preferred":[
        "\u0418\u0442\u0430\u0443\u0433\u0443\u0430"
    ],
    "name:eng_x_preferred":[
        "Itaugu\u00e1"
    ],
    "name:fas_x_preferred":[
        "\u0627\u06cc\u062a\u0627\u0626\u0648\u06af\u0648\u0622"
    ],
    "name:fra_x_preferred":[
        "Itaugu\u00e1"
    ],
    "name:grn_x_preferred":[
        "Ytaygua"
    ],
    "name:ita_x_preferred":[
        "Itaugu\u00e1"
    ],
    "name:kat_x_preferred":[
        "\u10d8\u10e2\u10d0\u10e3\u10d2\u10e3\u10d0"
    ],
    "name:lit_x_preferred":[
        "Itaugva"
    ],
    "name:nld_x_preferred":[
        "Itaugu\u00e1"
    ],
    "name:pol_x_preferred":[
        "Itaugu\u00e1"
    ],
    "name:rus_x_preferred":[
        "\u0418\u0442\u0430\u0443\u0433\u0443\u0430"
    ],
    "name:spa_x_preferred":[
        "Itaugu\u00e1"
    ],
    "name:zho_x_preferred":[
        "\u4f0a\u9676\u74dc"
    ],
    "qs:gn_country":"PY",
    "qs:gn_fcode":"PPL",
    "qs:gn_pop":64997,
    "qs:name":"Itaugu\u00e1",
    "qs:name_adm0":"Paraguay",
    "qs:name_adm1":"Central",
    "qs:photos":30,
    "qs:photos_1k":6,
    "qs:photos_9k":1,
    "qs:photos_9r":2,
    "qs:photos_all":30,
    "qs:photos_sr":2,
    "qs:placetype":"Town",
    "qs:pop_sr":"8",
    "qs:woe_adm0":23424917,
    "wd:wordcount":602,
    "wof:name":"Itaugu\u00e1",
    "wof:placetype":"locality",
    "wof:population":64997
},
  "geometry": {"coordinates":[-57.33333,-25.38333],"type":"Point"}
}