{
  "type": "Feature",
  "properties": {
    "gn:admin1_code":"7.0",
    "gn:admin2_code":"0101",
    "gn:asciiname":"Paso Horqueta",
    "gn:cc2":"PY",
    "gn:country_code":"PY",
    "gn:dem":89,
    "gn:feature_class":"P",
    "gn:feature_code":"PPL",
    "gn:name":"Paso Horqueta",
    "gn:population":0,
    "gn:timezone":"America/Asuncion",
    "iso:country":"PY",
    "name:und_x_variant":[
        "Paso Mancuello",
        "Paso Horqueta"
    ],
    "wof:name":"Paso Horqueta",
    "wof:placetype":"locality"
},
  "geometry": {"coordinates":[-57.39471999999999,-23.08806],"type":"Point"}
}