{
  "type": "Feature",
  "properties": {
    "gn:admin1_code":"23.0",
    "gn:admin2_code":"1704",
    "gn:asciiname":"Puerto Ramos",
    "gn:country_code":"PY",
    "gn:dem":86,
    "gn:feature_class":"P",
    "gn:feature_code":"PPL",
    "gn:name":"Puerto Ramos",
    "gn:population":0,
    "gn:timezone":"America/Asuncion",
    "iso:country":"PY",
    "wof:name":"Puerto Ramos",
    "wof:placetype":"locality"
},
  "geometry": {"coordinates":[-58.16667,-20.28333],"type":"Point"}
}