{
  "type": "Feature",
  "properties": {
    "gn:admin1_code":"7.0",
    "gn:admin2_code":"0103",
    "gn:asciiname":"Compania Gumersindo Sosa",
    "gn:cc2":"PY",
    "gn:country_code":"PY",
    "gn:dem":122,
    "gn:feature_class":"P",
    "gn:feature_code":"PPL",
    "gn:name":"Compa\u00f1\u00eda Gumersindo Sosa",
    "gn:population":0,
    "gn:timezone":"America/Asuncion",
    "iso:country":"PY",
    "name:und_x_variant":[
        "Capit\u00e1n Sosa",
        "Compa\u00f1\u00eda Gumersindo Sosa"
    ],
    "wof:name":"Compania Gumersindo Sosa",
    "wof:placetype":"locality"
},
  "geometry": {"coordinates":[-57.01861,-23.39917],"type":"Point"}
}