{
  "type": "Feature",
  "properties": {
    "gn:admin1_code":"16.0",
    "gn:admin2_code":"1502",
    "gn:asciiname":"Estancia Pozo Azul",
    "gn:country_code":"PY",
    "gn:dem":88,
    "gn:feature_class":"P",
    "gn:feature_code":"PPL",
    "gn:name":"Estancia Pozo Azul",
    "gn:population":0,
    "gn:timezone":"America/Asuncion",
    "iso:country":"PY",
    "wof:name":"Estancia Pozo Azul",
    "wof:placetype":"locality"
},
  "geometry": {"coordinates":[-58.25,-24.05],"type":"Point"}
}