{
  "type": "Feature",
  "properties": {
    "gn:admin1_code":"1.0",
    "gn:admin2_code":"1005",
    "gn:asciiname":"Puerto Embalse",
    "gn:country_code":"PY",
    "gn:dem":178,
    "gn:feature_class":"P",
    "gn:feature_code":"PPL",
    "gn:name":"Puerto Embalse",
    "gn:population":0,
    "gn:timezone":"America/Asuncion",
    "iso:country":"PY",
    "name:spa_x_preferred":[
        "Puerto Embalse"
    ],
    "wof:name":"Puerto Embalse",
    "wof:placetype":"locality"
},
  "geometry": {"coordinates":[-54.62515,-25.4584],"type":"Point"}
}