{
  "type": "Feature",
  "properties": {
    "iso:country":"PY",
    "name:grn_x_preferred":[
        "Karaguatay"
    ],
    "name:ita_x_preferred":[
        "Caraguatay"
    ],
    "name:por_x_preferred":[
        "Caraguatay"
    ],
    "name:ron_x_preferred":[
        "Caraguatay"
    ],
    "name:spa_x_preferred":[
        "Caraguatay"
    ],
    "name:zho_x_preferred":[
        "\u5361\u62c9\u74dc\u6cf0"
    ],
    "qs:gn_country":"PY",
    "qs:gn_fcode":"PPL",
    "qs:gn_pop":1637,
    "qs:name":"Caraguatay",
    "qs:name_adm0":"Paraguay",
    "qs:name_adm1":"Cordillera",
    "qs:photos":0,
    "qs:photos_1k":0,
    "qs:photos_9k":1,
    "qs:photos_9r":1,
    "qs:photos_all":4,
    "qs:photos_sr":0,
    "qs:placetype":"Town",
    "qs:pop_sr":"3",
    "qs:woe_adm0":23424917,
    "wd:wordcount":540,
    "wof:name":"Caraguatay",
    "wof:placetype":"locality",
    "wof:population":1637
},
  "geometry": {"coordinates":[-56.81667,-25.23333],"type":"Point"}
}