{
  "type": "Feature",
  "properties": {
    "gn:admin1_code":"16.0",
    "gn:admin2_code":"1506",
    "gn:asciiname":"Estancia Pariri",
    "gn:country_code":"PY",
    "gn:dem":67,
    "gn:feature_class":"P",
    "gn:feature_code":"PPL",
    "gn:name":"Estancia Parir\u00ed",
    "gn:population":0,
    "gn:timezone":"America/Asuncion",
    "iso:country":"PY",
    "wof:name":"Estancia Pariri",
    "wof:placetype":"locality"
},
  "geometry": {"coordinates":[-57.71666999999999,-25.16667],"type":"Point"}
}