{
  "type": "Feature",
  "properties": {
    "gn:admin1_code":"11.0",
    "gn:admin2_code":"0706",
    "gn:asciiname":"Puerto Tres Palmito",
    "gn:country_code":"PY",
    "gn:dem":81,
    "gn:feature_class":"P",
    "gn:feature_code":"PPL",
    "gn:name":"Puerto Tres Palmito",
    "gn:population":0,
    "gn:timezone":"America/Asuncion",
    "iso:country":"PY",
    "wof:name":"Puerto Tres Palmito",
    "wof:placetype":"locality"
},
  "geometry": {"coordinates":[-55.65,-27.36667000000001],"type":"Point"}
}