{
  "type": "Feature",
  "properties": {
    "gn:admin1_code":"16.0",
    "gn:admin2_code":"1504",
    "gn:asciiname":"Estancia Villa Rey",
    "gn:country_code":"PY",
    "gn:dem":68,
    "gn:feature_class":"P",
    "gn:feature_code":"PPL",
    "gn:name":"Estancia Villa Rey",
    "gn:population":0,
    "gn:timezone":"America/Asuncion",
    "iso:country":"PY",
    "name:und_x_variant":[
        "Villa Rey",
        "Estancia Villa Rey"
    ],
    "wof:name":"Estancia Villa Rey",
    "wof:placetype":"locality"
},
  "geometry": {"coordinates":[-57.23421999999999,-24.6922],"type":"Point"}
}