{
  "type": "Feature",
  "properties": {
    "gn:admin1_code":"11.0",
    "gn:admin2_code":"0719",
    "gn:asciiname":"Puerto Turi",
    "gn:country_code":"PY",
    "gn:dem":62,
    "gn:feature_class":"P",
    "gn:feature_code":"PPL",
    "gn:name":"Puerto Tur\u00ed",
    "gn:population":0,
    "gn:timezone":"America/Asuncion",
    "iso:country":"PY",
    "name:spa_x_preferred":[
        "Puerto Tur\u00ed"
    ],
    "wof:name":"Puerto Turi",
    "wof:placetype":"locality"
},
  "geometry": {"coordinates":[-56.76317,-27.40854],"type":"Point"}
}