{
  "type": "Feature",
  "properties": {
    "gn:admin1_code":"24.0",
    "gn:admin2_code":"1602",
    "gn:asciiname":"Estancia Ytororo",
    "gn:country_code":"PY",
    "gn:dem":140,
    "gn:feature_class":"P",
    "gn:feature_code":"PPL",
    "gn:name":"Estancia Ytoror\u00f3",
    "gn:population":0,
    "gn:timezone":"America/Asuncion",
    "iso:country":"PY",
    "wof:name":"Estancia Ytororo",
    "wof:placetype":"locality"
},
  "geometry": {"coordinates":[-60.31667,-23.45],"type":"Point"}
}