{
  "type": "Feature",
  "properties": {
    "gn:admin1_code":"24.0",
    "gn:admin2_code":"1602",
    "gn:asciiname":"Sargento Saracho",
    "gn:cc2":"PY",
    "gn:country_code":"PY",
    "gn:dem":177,
    "gn:feature_class":"P",
    "gn:feature_code":"PPL",
    "gn:name":"Sargento Saracho",
    "gn:population":0,
    "gn:timezone":"America/Asuncion",
    "iso:country":"PY",
    "name:und_x_variant":[
        "Paz Sold\u00e1n",
        "Sargento Saracho"
    ],
    "wof:name":"Sargento Saracho",
    "wof:placetype":"locality"
},
  "geometry": {"coordinates":[-61.08333,-22.85],"type":"Point"}
}