{
  "type": "Feature",
  "properties": {
    "gn:admin1_code":"4.0",
    "gn:admin2_code":"0506",
    "gn:asciiname":"Estancia Lagunita",
    "gn:country_code":"PY",
    "gn:dem":319,
    "gn:feature_class":"P",
    "gn:feature_code":"PPL",
    "gn:name":"Estancia Lagunita",
    "gn:population":0,
    "gn:timezone":"America/Asuncion",
    "iso:country":"PY",
    "name:spa_x_preferred":[
        "Estancia Lagunita"
    ],
    "wof:name":"Estancia Lagunita",
    "wof:placetype":"locality"
},
  "geometry": {"coordinates":[-55.95016999999999,-25.27076],"type":"Point"}
}