{
  "type": "Feature",
  "properties": {
    "gn:admin1_code":"24.0",
    "gn:admin2_code":"1605",
    "gn:asciiname":"Grunfeld",
    "gn:country_code":"PY",
    "gn:dem":127,
    "gn:feature_class":"P",
    "gn:feature_code":"PPL",
    "gn:name":"Grunfeld",
    "gn:population":0,
    "gn:timezone":"America/Asuncion",
    "iso:country":"PY",
    "name:deu_x_preferred":[
        "Gr\u00fcnfeld"
    ],
    "wof:name":"Grunfeld",
    "wof:placetype":"locality"
},
  "geometry": {"coordinates":[-59.87214,-22.45696],"type":"Point"}
}