{
  "type": "Feature",
  "properties": {
    "gn:admin1_code":"16.0",
    "gn:admin2_code":"1503",
    "gn:asciiname":"Pirizal",
    "gn:country_code":"PY",
    "gn:dem":98,
    "gn:feature_class":"P",
    "gn:feature_code":"PPL",
    "gn:name":"Pirizal",
    "gn:population":0,
    "gn:timezone":"America/Asuncion",
    "iso:country":"PY",
    "wof:name":"Pirizal",
    "wof:placetype":"locality"
},
  "geometry": {"coordinates":[-58.55,-22.25],"type":"Point"}
}