{
  "type": "Feature",
  "properties": {
    "iso:country":"PY",
    "name:ceb_x_preferred":[
        "Trinidad"
    ],
    "name:deu_x_preferred":[
        "Trinidad"
    ],
    "name:eng_x_preferred":[
        "Trinidad"
    ],
    "name:eus_x_preferred":[
        "Trinidad"
    ],
    "name:fra_x_preferred":[
        "Trinidad"
    ],
    "name:ita_x_preferred":[
        "Trinidad"
    ],
    "name:nld_x_preferred":[
        "Trinidad"
    ],
    "name:por_x_preferred":[
        "Trinidad"
    ],
    "name:ron_x_preferred":[
        "Trinidad"
    ],
    "name:spa_x_preferred":[
        "Trinidad"
    ],
    "name:zho_x_preferred":[
        "\u7279\u7acb\u5c3c\u9054"
    ],
    "qs:gn_country":"PY",
    "qs:gn_fcode":"PPL",
    "qs:gn_pop":2837,
    "qs:name":"Trinidad",
    "qs:name_adm0":"Paraguay",
    "qs:name_adm1":"Itap\u00faa",
    "qs:photos":231,
    "qs:photos_1k":47,
    "qs:photos_9k":1,
    "qs:photos_9r":4,
    "qs:photos_all":231,
    "qs:photos_sr":4,
    "qs:placetype":"Town",
    "qs:pop_sr":"4",
    "qs:woe_adm0":23424917,
    "wd:wordcount":135,
    "wof:name":"Trinidad",
    "wof:placetype":"locality",
    "wof:population":2837
},
  "geometry": {"coordinates":[-55.78333,-27.11667],"type":"Point"}
}