{
  "type": "Feature",
  "properties": {
    "gn:admin1_code":"16.0",
    "gn:asciiname":"Estancia Sorpresa",
    "gn:cc2":"PY",
    "gn:country_code":"PY",
    "gn:dem":133,
    "gn:feature_class":"P",
    "gn:feature_code":"PPL",
    "gn:name":"Estancia Sorpresa",
    "gn:population":0,
    "gn:timezone":"America/Asuncion",
    "iso:country":"PY",
    "name:und_x_variant":[
        "Nueva Sorpresa",
        "Fort\u00edn Sorpresa",
        "Fortin Sorpresa Nueva",
        "Fort\u00edn Sorpresa Viejo",
        "Sorpresa",
        "Sorpresa Nueva",
        "Estancia Sorpresa"
    ],
    "wof:name":"Estancia Sorpresa",
    "wof:placetype":"locality"
},
  "geometry": {"coordinates":[-60.05,-24.01667],"type":"Point"}
}