{
  "type": "Feature",
  "properties": {
    "gn:admin1_code":"12.0",
    "gn:admin2_code":"0801",
    "gn:asciiname":"Puesto Siete Palmas",
    "gn:country_code":"PY",
    "gn:dem":67,
    "gn:feature_class":"P",
    "gn:feature_code":"PPL",
    "gn:name":"Puesto Siete Palmas",
    "gn:population":0,
    "gn:timezone":"America/Asuncion",
    "iso:country":"PY",
    "name:spa_x_preferred":[
        "Puesto Siete Palmas"
    ],
    "name:und_x_variant":[
        "Puesto Siete Palma"
    ],
    "wof:name":"Puesto Siete Palmas",
    "wof:placetype":"locality"
},
  "geometry": {"coordinates":[-57.52462,-26.67351],"type":"Point"}
}