{
  "type": "Feature",
  "properties": {
    "gn:admin1_code":"7.0",
    "gn:admin2_code":"0107",
    "gn:asciiname":"Colonia Cerro Memby",
    "gn:country_code":"PY",
    "gn:dem":264,
    "gn:feature_class":"P",
    "gn:feature_code":"PPL",
    "gn:name":"Colonia Cerro Memby",
    "gn:population":0,
    "gn:timezone":"America/Asuncion",
    "iso:country":"PY",
    "wof:name":"Colonia Cerro Memby",
    "wof:placetype":"locality"
},
  "geometry": {"coordinates":[-56.36666999999999,-22.83333],"type":"Point"}
}