{
  "type": "Feature",
  "properties": {
    "gn:admin1_code":"5.0",
    "gn:admin2_code":"0604",
    "gn:asciiname":"Moises S. Bertoni",
    "gn:cc2":"PY",
    "gn:country_code":"PY",
    "gn:dem":117,
    "gn:feature_class":"P",
    "gn:feature_code":"PPL",
    "gn:name":"Mois\u00e9s S. Bertoni",
    "gn:population":0,
    "gn:timezone":"America/Asuncion",
    "iso:country":"PY",
    "name:und_x_variant":[
        "Colonia Moses Bertoni",
        "Mois\u00e9s Bertoni",
        "Colonia Moises Bertoni",
        "Mois\u00e9s S. Bertoni"
    ],
    "wof:name":"Moises S. Bertoni",
    "wof:placetype":"locality"
},
  "geometry": {"coordinates":[-56.43333000000001,-26.36667000000001],"type":"Point"}
}