{
  "type": "Feature",
  "properties": {
    "gn:admin1_code":"16.0",
    "gn:admin2_code":"1508",
    "gn:asciiname":"Estancia Agualinda",
    "gn:country_code":"PY",
    "gn:dem":130,
    "gn:feature_class":"P",
    "gn:feature_code":"PPL",
    "gn:name":"Estancia Agualinda",
    "gn:population":0,
    "gn:timezone":"America/Asuncion",
    "iso:country":"PY",
    "wof:name":"Estancia Agualinda",
    "wof:placetype":"locality"
},
  "geometry": {"coordinates":[-59.98333,-23.88333],"type":"Point"}
}