{
  "type": "Feature",
  "properties": {
    "gn:admin1_code":"16.0",
    "gn:admin2_code":"1503",
    "gn:asciiname":"Estancia San Pedro",
    "gn:cc2":"PY",
    "gn:country_code":"PY",
    "gn:dem":95,
    "gn:feature_class":"P",
    "gn:feature_code":"PPL",
    "gn:name":"Estancia San Pedro",
    "gn:population":0,
    "gn:timezone":"America/Asuncion",
    "iso:country":"PY",
    "name:und_x_variant":[
        "San Pedro",
        "Puerto San Pedro",
        "Estancia San Pedro"
    ],
    "wof:name":"Estancia San Pedro",
    "wof:placetype":"locality"
},
  "geometry": {"coordinates":[-58.43333000000001,-22.53333],"type":"Point"}
}