{
  "type": "Feature",
  "properties": {
    "gn:admin1_code":"16.0",
    "gn:asciiname":"Estancia San Jose",
    "gn:cc2":"PY",
    "gn:country_code":"PY",
    "gn:dem":91,
    "gn:feature_class":"P",
    "gn:feature_code":"PPL",
    "gn:name":"Estancia San Jos\u00e9",
    "gn:population":0,
    "gn:timezone":"America/Asuncion",
    "iso:country":"PY",
    "name:und_x_variant":[
        "San Jos\u00e9",
        "Estancia San Jos\u00e9"
    ],
    "wof:name":"Estancia San Jose",
    "wof:placetype":"locality"
},
  "geometry": {"coordinates":[-57.83333,-22.46667],"type":"Point"}
}