{
  "type": "Feature",
  "properties": {
    "gn:admin1_code":"23.0",
    "gn:admin2_code":"1704",
    "gn:asciiname":"Puerto Esperanza",
    "gn:cc2":"PY",
    "gn:country_code":"PY",
    "gn:dem":87,
    "gn:feature_class":"P",
    "gn:feature_code":"PPL",
    "gn:name":"Puerto Esperanza",
    "gn:population":0,
    "gn:timezone":"America/Asuncion",
    "iso:country":"PY",
    "name:und_x_variant":[
        "Esperanza",
        "Puerto Esperanza"
    ],
    "wof:name":"Puerto Esperanza",
    "wof:placetype":"locality"
},
  "geometry": {"coordinates":[-58.10111,-20.43252],"type":"Point"}
}