{
  "type": "Feature",
  "properties": {
    "gn:admin1_code":"16.0",
    "gn:admin2_code":"1504",
    "gn:asciiname":"Puerto Taruma",
    "gn:cc2":"PY",
    "gn:country_code":"PY",
    "gn:dem":72,
    "gn:feature_class":"P",
    "gn:feature_code":"PPL",
    "gn:name":"Puerto Tarum\u00e1",
    "gn:population":0,
    "gn:timezone":"America/Asuncion",
    "iso:country":"PY",
    "name:und_x_variant":[
        "Puesto Taruma",
        "Puerto Tarum\u00e1"
    ],
    "wof:name":"Puerto Taruma",
    "wof:placetype":"locality"
},
  "geometry": {"coordinates":[-57.58333,-23.63333],"type":"Point"}
}