{
  "type": "Feature",
  "properties": {
    "gn:admin1_code":"19.0",
    "gn:admin2_code":"1410",
    "gn:asciiname":"Colonia Parodi",
    "gn:country_code":"PY",
    "gn:dem":257,
    "gn:feature_class":"P",
    "gn:feature_code":"PPL",
    "gn:name":"Colonia Parodi",
    "gn:population":0,
    "gn:timezone":"America/Asuncion",
    "iso:country":"PY",
    "name:spa_x_preferred":[
        "Colonia Parodi"
    ],
    "name:und_x_variant":[
        "Parodi"
    ],
    "wof:name":"Colonia Parodi",
    "wof:placetype":"locality"
},
  "geometry": {"coordinates":[-54.3645,-24.67826],"type":"Point"}
}