{
  "type": "Feature",
  "properties": {
    "gn:admin1_code":"4.0",
    "gn:admin2_code":"0510",
    "gn:asciiname":"Estancia Taruma",
    "gn:country_code":"PY",
    "gn:dem":115,
    "gn:feature_class":"P",
    "gn:feature_code":"PPL",
    "gn:name":"Estancia Tarum\u00e1",
    "gn:population":0,
    "gn:timezone":"America/Asuncion",
    "iso:country":"PY",
    "name:spa_x_preferred":[
        "Estancia Tarum\u00e1"
    ],
    "wof:name":"Estancia Taruma",
    "wof:placetype":"locality"
},
  "geometry": {"coordinates":[-56.66947,-25.48487],"type":"Point"}
}