{
  "type": "Feature",
  "properties": {
    "gn:admin1_code":"24.0",
    "gn:admin2_code":"1602",
    "gn:asciiname":"Palma Chica",
    "gn:country_code":"PY",
    "gn:dem":194,
    "gn:feature_class":"P",
    "gn:feature_code":"PPL",
    "gn:name":"Palma Chica",
    "gn:population":0,
    "gn:timezone":"America/Asuncion",
    "iso:country":"PY",
    "wof:name":"Palma Chica",
    "wof:placetype":"locality"
},
  "geometry": {"coordinates":[-61.66667,-23.26667],"type":"Point"}
}