{
  "type": "Feature",
  "properties": {
    "gn:admin1_code":"5.0",
    "gn:admin2_code":"0601",
    "gn:asciiname":"Estancia San Nicolas",
    "gn:country_code":"PY",
    "gn:dem":128,
    "gn:feature_class":"P",
    "gn:feature_code":"PPL",
    "gn:name":"Estancia San Nicol\u00e1s",
    "gn:population":0,
    "gn:timezone":"America/Asuncion",
    "iso:country":"PY",
    "name:spa_x_preferred":[
        "Estancia San Nicol\u00e1s"
    ],
    "wof:name":"Estancia San Nicolas",
    "wof:placetype":"locality"
},
  "geometry": {"coordinates":[-56.24783000000001,-26.0774],"type":"Point"}
}