{
  "type": "Feature",
  "properties": {
    "gn:admin1_code":"2.0",
    "gn:admin2_code":"1302",
    "gn:asciiname":"Isla La Muerte",
    "gn:cc2":"PY",
    "gn:country_code":"PY",
    "gn:dem":176,
    "gn:feature_class":"P",
    "gn:feature_code":"PPL",
    "gn:name":"Isla La Muerte",
    "gn:population":0,
    "gn:timezone":"America/Asuncion",
    "iso:country":"PY",
    "name:und_x_variant":[
        "Isla La Muerta",
        "Isla La Muerte"
    ],
    "wof:name":"Isla La Muerte",
    "wof:placetype":"locality"
},
  "geometry": {"coordinates":[-56.66667,-22.55],"type":"Point"}
}