{
  "type": "Feature",
  "properties": {
    "iso:country":"PY",
    "name:ast_x_preferred":[
        "Piray\u00fa"
    ],
    "name:ceb_x_preferred":[
        "Piray\u00fa"
    ],
    "name:dan_x_preferred":[
        "Piray\u00fa"
    ],
    "name:deu_x_preferred":[
        "Piray\u00fa"
    ],
    "name:eng_x_preferred":[
        "Piray\u00fa"
    ],
    "name:eus_x_preferred":[
        "Piray\u00fa"
    ],
    "name:fra_x_preferred":[
        "Piray\u00fa"
    ],
    "name:ita_x_preferred":[
        "Piray\u00fa"
    ],
    "name:jpn_x_preferred":[
        "\u30d4\u30e9\u30e6"
    ],
    "name:nld_x_preferred":[
        "Piray\u00fa"
    ],
    "name:pol_x_preferred":[
        "Piray\u00fa"
    ],
    "name:por_x_preferred":[
        "Piray\u00fa"
    ],
    "name:spa_x_preferred":[
        "Piray\u00fa"
    ],
    "name:swe_x_preferred":[
        "Piray\u00fa"
    ],
    "name:zho_x_preferred":[
        "\u76ae\u62c9\u5c24"
    ],
    "qs:gn_country":"PY",
    "qs:gn_fcode":"PPL",
    "qs:gn_pop":4000,
    "qs:name":"Piray\u00fa",
    "qs:name_adm0":"Paraguay",
    "qs:name_adm1":"Paraguar\u00ed",
    "qs:photos":0,
    "qs:photos_1k":0,
    "qs:photos_9k":1,
    "qs:photos_9r":3,
    "qs:photos_all":149,
    "qs:photos_sr":0,
    "qs:placetype":"Town",
    "qs:pop_sr":"4",
    "qs:woe_adm0":23424917,
    "wd:wordcount":16,
    "wof:name":"Piray\u00fa",
    "wof:placetype":"locality",
    "wof:population":4000
},
  "geometry": {"coordinates":[-57.23333,-25.48333],"type":"Point"}
}