{
  "type": "Feature",
  "properties": {
    "gn:admin1_code":"7.0",
    "gn:admin2_code":"0101",
    "gn:asciiname":"Estancia Santa Maria",
    "gn:country_code":"PY",
    "gn:dem":179,
    "gn:feature_class":"P",
    "gn:feature_code":"PPL",
    "gn:name":"Estancia Santa Mar\u00eda",
    "gn:population":0,
    "gn:timezone":"America/Asuncion",
    "iso:country":"PY",
    "wof:name":"Estancia Santa Maria",
    "wof:placetype":"locality"
},
  "geometry": {"coordinates":[-57.46666999999999,-22.75],"type":"Point"}
}