{
  "type": "Feature",
  "properties": {
    "gn:admin1_code":"23.0",
    "gn:admin2_code":"1704",
    "gn:asciiname":"Puesto Warnes",
    "gn:country_code":"PY",
    "gn:dem":202,
    "gn:feature_class":"P",
    "gn:feature_code":"PPL",
    "gn:name":"Puesto Warnes",
    "gn:population":0,
    "gn:timezone":"America/Asuncion",
    "iso:country":"PY",
    "wof:name":"Puesto Warnes",
    "wof:placetype":"locality"
},
  "geometry": {"coordinates":[-60.75,-19.95],"type":"Point"}
}