{
  "type": "Feature",
  "properties": {
    "gn:admin1_code":"23.0",
    "gn:admin2_code":"1702",
    "gn:asciiname":"Estancia San Antonio",
    "gn:country_code":"PY",
    "gn:dem":82,
    "gn:feature_class":"P",
    "gn:feature_code":"PPL",
    "gn:name":"Estancia San Antonio",
    "gn:population":0,
    "gn:timezone":"America/Asuncion",
    "iso:country":"PY",
    "wof:name":"Estancia San Antonio",
    "wof:placetype":"locality"
},
  "geometry": {"coordinates":[-57.93333000000001,-21.16667],"type":"Point"}
}