{
  "type": "Feature",
  "properties": {
    "gn:admin1_code":"17.0",
    "gn:admin2_code":"0213",
    "gn:asciiname":"San Jose del Rosario",
    "gn:country_code":"PY",
    "gn:dem":104,
    "gn:feature_class":"P",
    "gn:feature_code":"PPL",
    "gn:name":"San Jos\u00e9 del Rosario",
    "gn:population":0,
    "gn:timezone":"America/Asuncion",
    "iso:country":"PY",
    "name:und_x_variant":[
        "Reducci\u00f3n de San Jos\u00e9",
        "San Jos\u00e9 del Rosario"
    ],
    "wof:name":"San Jose del Rosario",
    "wof:placetype":"locality"
},
  "geometry": {"coordinates":[-56.90296,-24.26515],"type":"Point"}
}