{
  "type": "Feature",
  "properties": {
    "gn:admin1_code":"23.0",
    "gn:admin2_code":"1704",
    "gn:asciiname":"Puesto Palmares",
    "gn:cc2":"PY",
    "gn:country_code":"PY",
    "gn:dem":156,
    "gn:feature_class":"P",
    "gn:feature_code":"PPL",
    "gn:name":"Puesto Palmares",
    "gn:population":0,
    "gn:timezone":"America/Asuncion",
    "iso:country":"PY",
    "name:und_x_variant":[
        "Puerto Palmares",
        "Puesto Palmares"
    ],
    "wof:name":"Puesto Palmares",
    "wof:placetype":"locality"
},
  "geometry": {"coordinates":[-60.15,-20.28333],"type":"Point"}
}