{
  "type": "Feature",
  "properties": {
    "gn:admin1_code":"23.0",
    "gn:admin2_code":"1705",
    "gn:asciiname":"Estancia Notice",
    "gn:country_code":"PY",
    "gn:dem":104,
    "gn:feature_class":"P",
    "gn:feature_code":"PPL",
    "gn:name":"Estancia Notice",
    "gn:population":0,
    "gn:timezone":"America/Asuncion",
    "iso:country":"PY",
    "wof:name":"Estancia Notice",
    "wof:placetype":"locality"
},
  "geometry": {"coordinates":[-58.46666999999999,-21.68333],"type":"Point"}
}