{
  "type": "Feature",
  "properties": {
    "gn:admin1_code":"23.0",
    "gn:admin2_code":"1705",
    "gn:asciiname":"Colonia Carmelo Peralta",
    "gn:country_code":"PY",
    "gn:dem":82,
    "gn:feature_class":"P",
    "gn:feature_code":"PPL",
    "gn:name":"Colonia Carmelo Peralta",
    "gn:population":0,
    "gn:timezone":"America/Asuncion",
    "iso:country":"PY",
    "wof:name":"Colonia Carmelo Peralta",
    "wof:placetype":"locality"
},
  "geometry": {"coordinates":[-57.95,-21.66667],"type":"Point"}
}