{
  "type": "Feature",
  "properties": {
    "gn:admin1_code":"23.0",
    "gn:admin2_code":"1701",
    "gn:asciiname":"Campamento Cabichu-i",
    "gn:country_code":"PY",
    "gn:dem":88,
    "gn:feature_class":"P",
    "gn:feature_code":"PPL",
    "gn:name":"Campamento Cabichu-\u00ed",
    "gn:population":0,
    "gn:timezone":"America/Asuncion",
    "iso:country":"PY",
    "wof:name":"Campamento Cabichu-i",
    "wof:placetype":"locality"
},
  "geometry": {"coordinates":[-58.48333,-20.38333],"type":"Point"}
}