{
  "type": "Feature",
  "properties": {
    "gn:admin1_code":"15.0",
    "gn:admin2_code":"0913",
    "gn:asciiname":"Colonia Santa Isabel",
    "gn:country_code":"PY",
    "gn:dem":190,
    "gn:feature_class":"P",
    "gn:feature_code":"PPLL",
    "gn:name":"Colonia Santa Isabel",
    "gn:population":0,
    "gn:timezone":"America/Asuncion",
    "iso:country":"PY",
    "name:spa_x_preferred":[
        "Colonia Santa Isabel"
    ],
    "wof:name":"Colonia Santa Isabel",
    "wof:placetype":"locality"
},
  "geometry": {"coordinates":[-56.94975,-25.74378],"type":"Point"}
}