{
  "type": "Feature",
  "properties": {
    "iso:country":"PY",
    "name:deu_x_preferred":[
        "Limpio"
    ],
    "name:epo_x_preferred":[
        "Limpio"
    ],
    "name:fas_x_preferred":[
        "\u0644\u06cc\u0645\u067e\u06cc\u0648"
    ],
    "name:fra_x_preferred":[
        "Limpio"
    ],
    "name:grn_x_preferred":[
        "Limpio"
    ],
    "name:hbs_x_preferred":[
        "Limpio"
    ],
    "name:ita_x_preferred":[
        "Limpio"
    ],
    "name:kat_x_preferred":[
        "\u10da\u10d8\u10db\u10de\u10d8\u10dd"
    ],
    "name:lit_x_preferred":[
        "Limpijus"
    ],
    "name:mkd_x_preferred":[
        "\u041b\u0438\u043c\u043f\u0438\u043e"
    ],
    "name:nld_x_preferred":[
        "Limpio"
    ],
    "name:pol_x_preferred":[
        "Limpio"
    ],
    "name:por_x_preferred":[
        "Limpio"
    ],
    "name:sco_x_preferred":[
        "Limpio"
    ],
    "name:spa_x_preferred":[
        "Limpio"
    ],
    "name:vol_x_preferred":[
        "Limpio"
    ],
    "name:zho_x_preferred":[
        "\u6797\u76ae\u5967"
    ],
    "qs:gn_country":"PY",
    "qs:gn_fcode":"PPL",
    "qs:gn_pop":96143,
    "qs:name":"Limpio",
    "qs:name_adm0":"Paraguay",
    "qs:name_adm1":"Central",
    "qs:photos":0,
    "qs:photos_1k":0,
    "qs:photos_9k":1,
    "qs:photos_9r":1,
    "qs:photos_all":3,
    "qs:photos_sr":0,
    "qs:placetype":"Town",
    "qs:pop_sr":"8",
    "qs:woe_adm0":23424917,
    "wof:name":"Limpio",
    "wof:placetype":"locality",
    "wof:population":96143
},
  "geometry": {"coordinates":[-57.48562,-25.16611],"type":"Point"}
}