{
  "type": "Feature",
  "properties": {
    "gn:admin1_code":"19.0",
    "gn:admin2_code":"1412",
    "gn:asciiname":"Colonia Santo Domingo",
    "gn:country_code":"PY",
    "gn:dem":302,
    "gn:feature_class":"P",
    "gn:feature_code":"PPL",
    "gn:name":"Colonia Santo Domingo",
    "gn:population":0,
    "gn:timezone":"America/Asuncion",
    "iso:country":"PY",
    "name:spa_x_preferred":[
        "Colonia Santo Domingo"
    ],
    "name:und_x_variant":[
        "Santo Domingo"
    ],
    "wof:name":"Colonia Santo Domingo",
    "wof:placetype":"locality"
},
  "geometry": {"coordinates":[-55.12393,-24.38123],"type":"Point"}
}