{
  "type": "Feature",
  "properties": {
    "iso:country":"PY",
    "name:ceb_x_preferred":[
        "San Juan Neembuc\u00fa"
    ],
    "name:eus_x_preferred":[
        "San Juan Bautista del \u00d1eembuc\u00fa"
    ],
    "name:grn_x_preferred":[
        "San Juan Bautista del \u00d1e'embuku"
    ],
    "name:ita_x_preferred":[
        "San Juan Bautista de \u00d1eembuc\u00fa"
    ],
    "name:por_x_preferred":[
        "San Juan Bautista del \u00d1eembuc\u00fa"
    ],
    "name:spa_x_preferred":[
        "San Juan Bautista del \u00d1eembuc\u00fa"
    ],
    "name:unk_x_variant":[
        "San Juan Bautista \u00d1eembuc\u00fa"
    ],
    "name:zho_x_preferred":[
        "\u8056\u80e1\u5b89\u5305\u8482\u65af\u5854\u5fb7\u723e\u6d85\u6069\u5e03\u5eab"
    ],
    "qs:gn_country":"PY",
    "qs:gn_fcode":"PPL",
    "qs:gn_pop":330,
    "qs:name":"San Juan Bautista de \u00d1eembuc\u00fa",
    "qs:name_adm0":"Paraguay",
    "qs:name_adm1":"\u00d1eembuc\u00fa",
    "qs:photos":0,
    "qs:photos_1k":0,
    "qs:photos_9k":0,
    "qs:photos_9r":0,
    "qs:photos_all":0,
    "qs:photos_sr":0,
    "qs:placetype":"Town",
    "qs:pop_sr":"2",
    "qs:woe_adm0":23424917,
    "wd:wordcount":28,
    "wof:name":"San Juan Bautista de \u00d1eembuc\u00fa",
    "wof:placetype":"locality",
    "wof:population":330
},
  "geometry": {"coordinates":[-57.93333,-26.65],"type":"Point"}
}