{
  "type": "Feature",
  "properties": {
    "gn:admin1_code":"5.0",
    "gn:admin2_code":"0609",
    "gn:asciiname":"Canete",
    "gn:cc2":"PY",
    "gn:country_code":"PY",
    "gn:dem":88,
    "gn:feature_class":"P",
    "gn:feature_code":"PPL",
    "gn:name":"Ca\u00f1ete",
    "gn:population":0,
    "gn:timezone":"America/Asuncion",
    "iso:country":"PY",
    "name:und_x_variant":[
        "Ca\u00f1ete-cue",
        "Ca\u00f1ete"
    ],
    "wof:name":"Canete",
    "wof:placetype":"locality"
},
  "geometry": {"coordinates":[-56.45,-26.56667],"type":"Point"}
}