{
  "type": "Feature",
  "properties": {
    "gn:admin1_code":"16.0",
    "gn:admin2_code":"1507",
    "gn:asciiname":"Diez Caballos",
    "gn:country_code":"PY",
    "gn:dem":131,
    "gn:feature_class":"P",
    "gn:feature_code":"PPL",
    "gn:name":"Diez Caballos",
    "gn:population":0,
    "gn:timezone":"America/Asuncion",
    "iso:country":"PY",
    "wof:name":"Diez Caballos",
    "wof:placetype":"locality"
},
  "geometry": {"coordinates":[-59.96666999999999,-23.61667000000001],"type":"Point"}
}