{
  "type": "Feature",
  "properties": {
    "gn:admin1_code":"7.0",
    "gn:admin2_code":"0105",
    "gn:asciiname":"Estancia San Luis",
    "gn:cc2":"PY",
    "gn:country_code":"PY",
    "gn:dem":188,
    "gn:feature_class":"P",
    "gn:feature_code":"PPL",
    "gn:name":"Estancia San Luis",
    "gn:population":0,
    "gn:timezone":"America/Asuncion",
    "iso:country":"PY",
    "name:und_x_variant":[
        "San Luis de la Sierra",
        "Estancia San Luis"
    ],
    "wof:name":"Estancia San Luis",
    "wof:placetype":"locality"
},
  "geometry": {"coordinates":[-57.45,-22.43333],"type":"Point"}
}