{
  "type": "Feature",
  "properties": {
    "gn:admin1_code":"11.0",
    "gn:admin2_code":"0716",
    "gn:asciiname":"Colonia Capitan F. Leguizamon",
    "gn:country_code":"PY",
    "gn:dem":119,
    "gn:feature_class":"P",
    "gn:feature_code":"PPL",
    "gn:name":"Colonia Capit\u00e1n F. Leguizam\u00f3n",
    "gn:population":0,
    "gn:timezone":"America/Asuncion",
    "iso:country":"PY",
    "wof:name":"Colonia Capitan F. Leguizamon",
    "wof:placetype":"locality"
},
  "geometry": {"coordinates":[-56.23333,-26.75],"type":"Point"}
}