{
  "type": "Feature",
  "properties": {
    "gn:admin1_code":"17.0",
    "gn:admin2_code":"0205",
    "gn:asciiname":"Compania Carolina",
    "gn:country_code":"PY",
    "gn:dem":116,
    "gn:feature_class":"P",
    "gn:feature_code":"PPL",
    "gn:name":"Compa\u00f1\u00eda Carolina",
    "gn:population":0,
    "gn:timezone":"America/Asuncion",
    "iso:country":"PY",
    "name:spa_x_preferred":[
        "Compa\u00f1\u00eda Carolina"
    ],
    "name:und_x_variant":[
        "Carolina"
    ],
    "wof:name":"Compania Carolina",
    "wof:placetype":"locality"
},
  "geometry": {"coordinates":[-56.69015,-24.58047],"type":"Point"}
}