{
  "type": "Feature",
  "properties": {
    "gn:admin1_code":"17.0",
    "gn:admin2_code":"0218",
    "gn:asciiname":"Estancia Rio Verde",
    "gn:country_code":"PY",
    "gn:dem":137,
    "gn:feature_class":"P",
    "gn:feature_code":"PPL",
    "gn:name":"Estancia Rio Verde",
    "gn:population":0,
    "gn:timezone":"America/Asuncion",
    "iso:country":"PY",
    "wof:name":"Estancia Rio Verde",
    "wof:placetype":"locality"
},
  "geometry": {"coordinates":[-56.13333000000001,-23.86667000000001],"type":"Point"}
}