{
  "type": "Feature",
  "properties": {
    "gn:admin1_code":"7.0",
    "gn:admin2_code":"0101",
    "gn:asciiname":"Puerto Abente",
    "gn:country_code":"PY",
    "gn:dem":75,
    "gn:feature_class":"P",
    "gn:feature_code":"PPL",
    "gn:name":"Puerto Abente",
    "gn:population":0,
    "gn:timezone":"America/Asuncion",
    "iso:country":"PY",
    "wof:name":"Puerto Abente",
    "wof:placetype":"locality"
},
  "geometry": {"coordinates":[-57.71666999999999,-22.91667],"type":"Point"}
}