{
  "type": "Feature",
  "properties": {
    "gn:admin1_code":"17.0",
    "gn:admin2_code":"0201",
    "gn:asciiname":"Estancia Serratti",
    "gn:country_code":"PY",
    "gn:dem":69,
    "gn:feature_class":"P",
    "gn:feature_code":"PPL",
    "gn:name":"Estancia Serratti",
    "gn:population":0,
    "gn:timezone":"America/Asuncion",
    "iso:country":"PY",
    "wof:name":"Estancia Serratti",
    "wof:placetype":"locality"
},
  "geometry": {"coordinates":[-57.19444,-23.89583],"type":"Point"}
}