{
  "type": "Feature",
  "properties": {
    "gn:admin1_code":"12.0",
    "gn:admin2_code":"0804",
    "gn:asciiname":"Estancia Santo Tomas",
    "gn:country_code":"PY",
    "gn:dem":88,
    "gn:feature_class":"P",
    "gn:feature_code":"PPL",
    "gn:name":"Estancia Santo Tom\u00e1s",
    "gn:population":0,
    "gn:timezone":"America/Asuncion",
    "iso:country":"PY",
    "wof:name":"Estancia Santo Tomas",
    "wof:placetype":"locality"
},
  "geometry": {"coordinates":[-56.88333000000001,-26.58333],"type":"Point"}
}