{
  "type": "Feature",
  "properties": {
    "gn:admin1_code":"1.0",
    "gn:admin2_code":"1014",
    "gn:asciiname":"San Alfredo",
    "gn:country_code":"PY",
    "gn:dem":235,
    "gn:feature_class":"P",
    "gn:feature_code":"PPL",
    "gn:name":"San Alfredo",
    "gn:population":0,
    "gn:timezone":"America/Asuncion",
    "iso:country":"PY",
    "name:spa_x_preferred":[
        "San Alfredo"
    ],
    "name:und_x_variant":[
        "Colonia San Alfredo"
    ],
    "wof:name":"San Alfredo",
    "wof:placetype":"locality"
},
  "geometry": {"coordinates":[-55.12801999999999,-26.03616],"type":"Point"}
}