{
  "type": "Feature",
  "properties": {
    "gn:admin1_code":"16.0",
    "gn:admin2_code":"1509",
    "gn:asciiname":"Estancia Laguna Bella",
    "gn:country_code":"PY",
    "gn:dem":108,
    "gn:feature_class":"P",
    "gn:feature_code":"PPL",
    "gn:name":"Estancia Laguna Bella",
    "gn:population":0,
    "gn:timezone":"America/Asuncion",
    "iso:country":"PY",
    "wof:name":"Estancia Laguna Bella",
    "wof:placetype":"locality"
},
  "geometry": {"coordinates":[-59.18333000000001,-24.38333],"type":"Point"}
}