{
  "type": "Feature",
  "properties": {
    "iso:country":"PY",
    "name:ceb_x_preferred":[
        "Tacuat\u00ed"
    ],
    "name:eng_x_preferred":[
        "Tacuat\u00ed"
    ],
    "name:eus_x_preferred":[
        "Tacuat\u00ed"
    ],
    "name:fra_x_preferred":[
        "Tacuat\u00ed"
    ],
    "name:ita_x_preferred":[
        "Tacuat\u00ed"
    ],
    "name:nld_x_preferred":[
        "Tacuat\u00ed"
    ],
    "name:por_x_preferred":[
        "Tacuat\u00ed"
    ],
    "name:spa_x_preferred":[
        "Tacuat\u00ed"
    ],
    "name:unk_x_variant":[
        "Tacuaty"
    ],
    "name:zho_x_preferred":[
        "\u5854\u5938\u8482"
    ],
    "qs:gn_country":"PY",
    "qs:gn_fcode":"PPL",
    "qs:gn_pop":2405,
    "qs:name":"Tacuat\u00ed",
    "qs:name_adm0":"Paraguay",
    "qs:name_adm1":"San Pedro",
    "qs:photos":0,
    "qs:photos_1k":0,
    "qs:photos_9k":0,
    "qs:photos_9r":0,
    "qs:photos_all":0,
    "qs:photos_sr":0,
    "qs:placetype":"Town",
    "qs:pop_sr":"4",
    "qs:woe_adm0":23424917,
    "wd:wordcount":154,
    "wof:name":"Tacuat\u00ed",
    "wof:placetype":"locality",
    "wof:population":2405
},
  "geometry": {"coordinates":[-56.58333,-23.45],"type":"Point"}
}