{
  "type": "Feature",
  "properties": {
    "gn:admin1_code":"22.0",
    "gn:admin2_code":"0000",
    "gn:asciiname":"San Blas",
    "gn:country_code":"PY",
    "gn:dem":64,
    "gn:feature_class":"P",
    "gn:feature_code":"PPLL",
    "gn:name":"San Bl\u00e1s",
    "gn:population":0,
    "gn:timezone":"America/Asuncion",
    "iso:country":"PY",
    "name:arg_x_preferred":[
        "Sant Blas"
    ],
    "name:cat_x_preferred":[
        "San Blas"
    ],
    "name:ceb_x_preferred":[
        "San Blas"
    ],
    "name:ces_x_preferred":[
        "San Blas"
    ],
    "name:deu_x_preferred":[
        "San Blas"
    ],
    "name:fra_x_preferred":[
        "San Blas"
    ],
    "name:kor_x_preferred":[
        "\uc0b0\ube14\ub77c\uc2a4"
    ],
    "name:nld_x_preferred":[
        "San Blas"
    ],
    "name:nor_x_preferred":[
        "San Blas"
    ],
    "name:pol_x_preferred":[
        "San Blas"
    ],
    "name:por_x_preferred":[
        "San Blas"
    ],
    "name:rus_x_preferred":[
        "\u0421\u0430\u043d-\u0411\u043b\u0430\u0441"
    ],
    "name:sco_x_preferred":[
        "San Blas"
    ],
    "name:spa_x_preferred":[
        "San Bl\u00e1s"
    ],
    "name:spa_x_variant":[
        "San Blas"
    ],
    "name:srp_x_preferred":[
        "\u0421\u0430\u043d \u0411\u043b\u0430\u0441"
    ],
    "name:swe_x_preferred":[
        "San Blas"
    ],
    "name:tur_x_preferred":[
        "San Blas"
    ],
    "name:und_x_variant":[
        "Barrio San Blas"
    ],
    "wof:name":"San Blas",
    "wof:placetype":"locality"
},
  "geometry": {"coordinates":[-57.57142,-25.22699],"type":"Point"}
}