{
  "type": "Feature",
  "properties": {
    "gn:admin1_code":"11.0",
    "gn:admin2_code":"0706",
    "gn:asciiname":"Puerto Paraiso",
    "gn:country_code":"PY",
    "gn:dem":150,
    "gn:feature_class":"P",
    "gn:feature_code":"PPL",
    "gn:name":"Puerto Paraiso",
    "gn:population":0,
    "gn:timezone":"America/Asuncion",
    "iso:country":"PY",
    "wof:name":"Puerto Paraiso",
    "wof:placetype":"locality"
},
  "geometry": {"coordinates":[-55.61666999999999,-27.28333],"type":"Point"}
}