{
  "type": "Feature",
  "properties": {
    "gn:admin1_code":"24.0",
    "gn:admin2_code":"1602",
    "gn:asciiname":"Puesto Subieta",
    "gn:country_code":"PY",
    "gn:dem":226,
    "gn:feature_class":"P",
    "gn:feature_code":"PPL",
    "gn:name":"Puesto Subieta",
    "gn:population":0,
    "gn:timezone":"America/Asuncion",
    "iso:country":"PY",
    "wof:name":"Puesto Subieta",
    "wof:placetype":"locality"
},
  "geometry": {"coordinates":[-62.05,-22.48333],"type":"Point"}
}