{
  "type": "Feature",
  "properties": {
    "gn:admin1_code":"6.0",
    "gn:admin2_code":"1116",
    "gn:asciiname":"Angostura",
    "gn:country_code":"PY",
    "gn:dem":65,
    "gn:feature_class":"P",
    "gn:feature_code":"PPLL",
    "gn:name":"Angostura",
    "gn:population":0,
    "gn:timezone":"America/Asuncion",
    "iso:country":"PY",
    "name:ceb_x_preferred":[
        "Angostura"
    ],
    "name:deu_x_preferred":[
        "Angostura"
    ],
    "name:eus_x_preferred":[
        "Angostura"
    ],
    "name:fra_x_preferred":[
        "Angostura"
    ],
    "name:glg_x_preferred":[
        "Angostura"
    ],
    "name:ita_x_preferred":[
        "Angostura"
    ],
    "name:nld_x_preferred":[
        "Angostura"
    ],
    "name:por_x_preferred":[
        "Angostura"
    ],
    "name:rus_x_preferred":[
        "\u0410\u043d\u0433\u043e\u0441\u0442\u0443\u0440\u0430"
    ],
    "name:sco_x_preferred":[
        "Angostura"
    ],
    "name:spa_x_preferred":[
        "Angostura"
    ],
    "name:srp_x_preferred":[
        "\u0410\u043d\u0433\u043e\u0441\u0442\u0443\u0440\u0430"
    ],
    "name:swe_x_preferred":[
        "Angostura"
    ],
    "wof:name":"Angostura",
    "wof:placetype":"locality"
},
  "geometry": {"coordinates":[-57.57216999999999,-25.57087000000001],"type":"Point"}
}