{
  "type": "Feature",
  "properties": {
    "gn:admin1_code":"4.0",
    "gn:admin2_code":"0515",
    "gn:asciiname":"Jose Domingo Ocampo",
    "gn:country_code":"PY",
    "gn:dem":262,
    "gn:feature_class":"P",
    "gn:feature_code":"PPL",
    "gn:name":"Jos\u00e9 Domingo Ocampo",
    "gn:population":0,
    "gn:timezone":"America/Asuncion",
    "iso:country":"PY",
    "name:spa_x_preferred":[
        "Jos\u00e9 Domingo Ocampo"
    ],
    "name:und_x_variant":[
        "J. D. Ocampos"
    ],
    "wof:name":"Jose Domingo Ocampo",
    "wof:placetype":"locality"
},
  "geometry": {"coordinates":[-55.43026999999999,-25.4121],"type":"Point"}
}