{
  "type": "Feature",
  "properties": {
    "gn:admin1_code":"15.0",
    "gn:admin2_code":"0908",
    "gn:asciiname":"Arroyo Costa",
    "gn:country_code":"PY",
    "gn:dem":98,
    "gn:feature_class":"P",
    "gn:feature_code":"PPL",
    "gn:name":"Arroyo Costa",
    "gn:population":0,
    "gn:timezone":"America/Asuncion",
    "iso:country":"PY",
    "wof:name":"Arroyo Costa",
    "wof:placetype":"locality"
},
  "geometry": {"coordinates":[-56.85,-26.18333],"type":"Point"}
}