{
  "type": "Feature",
  "properties": {
    "gn:admin1_code":"23.0",
    "gn:admin2_code":"1704",
    "gn:asciiname":"Santa Maria",
    "gn:country_code":"PY",
    "gn:dem":83,
    "gn:feature_class":"P",
    "gn:feature_code":"PPL",
    "gn:name":"Santa Mar\u00eda",
    "gn:population":0,
    "gn:timezone":"America/Asuncion",
    "iso:country":"PY",
    "wof:name":"Santa Maria",
    "wof:placetype":"locality"
},
  "geometry": {"coordinates":[-58.11666999999999,-20.41667],"type":"Point"}
}