{
  "type": "Feature",
  "properties": {
    "gn:admin1_code":"1.0",
    "gn:admin2_code":"1005",
    "gn:asciiname":"Colonia Laura",
    "gn:country_code":"PY",
    "gn:dem":247,
    "gn:feature_class":"P",
    "gn:feature_code":"PPLL",
    "gn:name":"Colonia Laura",
    "gn:population":0,
    "gn:timezone":"America/Asuncion",
    "iso:country":"PY",
    "name:spa_x_preferred":[
        "Colonia Laura"
    ],
    "wof:name":"Colonia Laura",
    "wof:placetype":"locality"
},
  "geometry": {"coordinates":[-54.92835,-25.26939],"type":"Point"}
}