{
  "type": "Feature",
  "properties": {
    "gn:admin1_code":"16.0",
    "gn:admin2_code":"1509",
    "gn:asciiname":"Estancia Cerrito Amakera",
    "gn:country_code":"PY",
    "gn:dem":106,
    "gn:feature_class":"P",
    "gn:feature_code":"PPL",
    "gn:name":"Estancia Cerrito Amakera",
    "gn:population":0,
    "gn:timezone":"America/Asuncion",
    "iso:country":"PY",
    "wof:name":"Estancia Cerrito Amakera",
    "wof:placetype":"locality"
},
  "geometry": {"coordinates":[-58.98333,-23.78333],"type":"Point"}
}