{
  "type": "Feature",
  "properties": {
    "gn:admin1_code":"13.0",
    "gn:admin2_code":"1203",
    "gn:asciiname":"Puerto Curuzu Aba",
    "gn:country_code":"PY",
    "gn:dem":61,
    "gn:feature_class":"P",
    "gn:feature_code":"PPL",
    "gn:name":"Puerto Curuz\u00fa Ab\u00e1",
    "gn:population":0,
    "gn:timezone":"America/Asuncion",
    "iso:country":"PY",
    "name:und_x_variant":[
        "Curuz\u00faab\u00e1",
        "Puerto Curuz\u00fa Ab\u00e1"
    ],
    "wof:name":"Puerto Curuzu Aba",
    "wof:placetype":"locality"
},
  "geometry": {"coordinates":[-57.79895,-27.27943],"type":"Point"}
}