{
  "type": "Feature",
  "properties": {
    "gn:admin1_code":"16.0",
    "gn:admin2_code":"1506",
    "gn:asciiname":"Estancia Mamo Rei",
    "gn:country_code":"PY",
    "gn:dem":69,
    "gn:feature_class":"P",
    "gn:feature_code":"PPL",
    "gn:name":"Estancia Mamo Re\u00ed",
    "gn:population":0,
    "gn:timezone":"America/Asuncion",
    "iso:country":"PY",
    "wof:name":"Estancia Mamo Rei",
    "wof:placetype":"locality"
},
  "geometry": {"coordinates":[-57.78333000000001,-25.11667000000001],"type":"Point"}
}