{
  "type": "Feature",
  "properties": {
    "gn:admin1_code":"8.0",
    "gn:admin2_code":"0306",
    "gn:asciiname":"Estancia Roja-Cue",
    "gn:country_code":"PY",
    "gn:dem":72,
    "gn:feature_class":"P",
    "gn:feature_code":"PPL",
    "gn:name":"Estancia Roja-Cu\u00e9",
    "gn:population":0,
    "gn:timezone":"America/Asuncion",
    "iso:country":"PY",
    "wof:name":"Estancia Roja-Cue",
    "wof:placetype":"locality"
},
  "geometry": {"coordinates":[-57.36666999999999,-25.15],"type":"Point"}
}