{
  "type": "Feature",
  "properties": {
    "gn:admin1_code":"17.0",
    "gn:admin2_code":"0208",
    "gn:asciiname":"Colonia Vacajhu",
    "gn:country_code":"PY",
    "gn:dem":132,
    "gn:feature_class":"P",
    "gn:feature_code":"PPL",
    "gn:name":"Colonia Vacajh\u00fa",
    "gn:population":0,
    "gn:timezone":"America/Asuncion",
    "iso:country":"PY",
    "name:spa_x_preferred":[
        "Colonia Vacajh\u00fa"
    ],
    "name:und_x_variant":[
        "Vaca Jhu"
    ],
    "wof:name":"Colonia Vacajhu",
    "wof:placetype":"locality"
},
  "geometry": {"coordinates":[-56.59882,-24.58162],"type":"Point"}
}