{
  "type": "Feature",
  "properties": {
    "gn:admin1_code":"7.0",
    "gn:asciiname":"Pindura-cue",
    "gn:cc2":"PY",
    "gn:country_code":"PY",
    "gn:dem":137,
    "gn:feature_class":"P",
    "gn:feature_code":"PPL",
    "gn:name":"Pindura-cu\u00e9",
    "gn:population":0,
    "gn:timezone":"America/Asuncion",
    "iso:country":"PY",
    "name:und_x_variant":[
        "Estancia Pindura-cu\u00e9",
        "Pindura-cu\u00e9"
    ],
    "wof:name":"Pindura-cue",
    "wof:placetype":"locality"
},
  "geometry": {"coordinates":[-56.66667,-22.85],"type":"Point"}
}