{
  "type": "Feature",
  "properties": {
    "gn:admin1_code":"15.0",
    "gn:admin2_code":"0902",
    "gn:asciiname":"Costa Pena",
    "gn:country_code":"PY",
    "gn:dem":182,
    "gn:feature_class":"P",
    "gn:feature_code":"PPLL",
    "gn:name":"Costa Pe\u00f1a",
    "gn:population":0,
    "gn:timezone":"America/Asuncion",
    "iso:country":"PY",
    "name:spa_x_preferred":[
        "Costa Pe\u00f1a"
    ],
    "wof:name":"Costa Pena",
    "wof:placetype":"locality"
},
  "geometry": {"coordinates":[-56.97094,-25.87976],"type":"Point"}
}