{
  "type": "Feature",
  "properties": {
    "gn:admin1_code":"5.0",
    "gn:admin2_code":"0609",
    "gn:asciiname":"Canete-cue",
    "gn:country_code":"PY",
    "gn:dem":80,
    "gn:feature_class":"P",
    "gn:feature_code":"PPL",
    "gn:name":"Ca\u00f1ete-cu\u00e9",
    "gn:population":0,
    "gn:timezone":"America/Asuncion",
    "iso:country":"PY",
    "wof:name":"Canete-cue",
    "wof:placetype":"locality"
},
  "geometry": {"coordinates":[-56.71666999999999,-26.55],"type":"Point"}
}