{
  "type": "Feature",
  "properties": {
    "gn:admin1_code":"24.0",
    "gn:admin2_code":"1602",
    "gn:asciiname":"Estancia Nandu",
    "gn:country_code":"PY",
    "gn:dem":166,
    "gn:feature_class":"P",
    "gn:feature_code":"PPL",
    "gn:name":"Estancia \u00d1and\u00fa",
    "gn:population":0,
    "gn:timezone":"America/Asuncion",
    "iso:country":"PY",
    "wof:name":"Estancia Nandu",
    "wof:placetype":"locality"
},
  "geometry": {"coordinates":[-60.76667,-22.55],"type":"Point"}
}