{
  "type": "Feature",
  "properties": {
    "gn:admin1_code":"16.0",
    "gn:admin2_code":"1504",
    "gn:asciiname":"Puesto Estrella",
    "gn:country_code":"PY",
    "gn:dem":107,
    "gn:feature_class":"P",
    "gn:feature_code":"PPL",
    "gn:name":"Puesto Estrella",
    "gn:population":0,
    "gn:timezone":"America/Asuncion",
    "iso:country":"PY",
    "wof:name":"Puesto Estrella",
    "wof:placetype":"locality"
},
  "geometry": {"coordinates":[-58.88333000000001,-23.25],"type":"Point"}
}