{
  "type": "Feature",
  "properties": {
    "gn:admin1_code":"4.0",
    "gn:admin2_code":"0510",
    "gn:asciiname":"Cristo Rey",
    "gn:country_code":"PY",
    "gn:dem":144,
    "gn:feature_class":"P",
    "gn:feature_code":"PPL",
    "gn:name":"Cristo Rey",
    "gn:population":0,
    "gn:timezone":"America/Asuncion",
    "iso:country":"PY",
    "wof:name":"Cristo Rey",
    "wof:placetype":"locality"
},
  "geometry": {"coordinates":[-56.66667,-25.56667],"type":"Point"}
}