{
  "type": "Feature",
  "properties": {
    "gn:admin1_code":"7.0",
    "gn:admin2_code":"0109",
    "gn:asciiname":"Estancia San Rafael",
    "gn:cc2":"PY",
    "gn:country_code":"PY",
    "gn:dem":156,
    "gn:feature_class":"P",
    "gn:feature_code":"PPL",
    "gn:name":"Estancia San Rafael",
    "gn:population":0,
    "gn:timezone":"America/Asuncion",
    "iso:country":"PY",
    "name:und_x_variant":[
        "San Rafael",
        "Rafa",
        "Estancia San Rafael"
    ],
    "wof:name":"Estancia San Rafael",
    "wof:placetype":"locality"
},
  "geometry": {"coordinates":[-56.73333,-22.61667000000001],"type":"Point"}
}