{
  "type": "Feature",
  "properties": {
    "gn:admin1_code":"2.0",
    "gn:admin2_code":"1302",
    "gn:asciiname":"Peguajho",
    "gn:country_code":"PY",
    "gn:dem":235,
    "gn:feature_class":"P",
    "gn:feature_code":"PPL",
    "gn:name":"Peguajh\u00f3",
    "gn:population":0,
    "gn:timezone":"America/Asuncion",
    "iso:country":"PY",
    "wof:name":"Peguajho",
    "wof:placetype":"locality"
},
  "geometry": {"coordinates":[-56.38333000000001,-22.26667],"type":"Point"}
}