{
  "type": "Feature",
  "properties": {
    "gn:admin1_code":"24.0",
    "gn:admin2_code":"1604",
    "gn:asciiname":"Puesto Teniente G. Trovatto",
    "gn:country_code":"PY",
    "gn:dem":164,
    "gn:feature_class":"P",
    "gn:feature_code":"PPL",
    "gn:name":"Puesto Teniente G. Trovatto",
    "gn:population":0,
    "gn:timezone":"America/Asuncion",
    "iso:country":"PY",
    "wof:name":"Puesto Teniente G. Trovatto",
    "wof:placetype":"locality"
},
  "geometry": {"coordinates":[-60.45,-21.96667],"type":"Point"}
}