{
  "type": "Feature",
  "properties": {
    "iso:country":"PY",
    "name:eng_x_preferred":[
        "\u00d1um\u00ed"
    ],
    "name:eus_x_preferred":[
        "\u00d1um\u00ed"
    ],
    "name:fra_x_preferred":[
        "\u00d1um\u00ed"
    ],
    "name:grn_x_preferred":[
        "\u00d1umi"
    ],
    "name:ita_x_preferred":[
        "\u00d1um\u00ed"
    ],
    "name:nld_x_preferred":[
        "\u00d1um\u00ed"
    ],
    "name:por_x_preferred":[
        "\u00d1um\u00ed"
    ],
    "name:spa_x_preferred":[
        "\u00d1um\u00ed"
    ],
    "name:zho_x_preferred":[
        "\u7d10\u7c73"
    ],
    "qs:gn_country":"PY",
    "qs:gn_fcode":"PPL",
    "qs:gn_pop":864,
    "qs:name":"\u00d1um\u00ed",
    "qs:name_adm0":"Paraguay",
    "qs:name_adm1":"Guair\u00e1",
    "qs:photos":0,
    "qs:photos_1k":0,
    "qs:photos_9k":0,
    "qs:photos_9r":0,
    "qs:photos_all":0,
    "qs:photos_sr":0,
    "qs:placetype":"Town",
    "qs:pop_sr":"2",
    "qs:woe_adm0":23424917,
    "wd:wordcount":658,
    "wof:name":"\u00d1um\u00ed",
    "wof:placetype":"locality",
    "wof:population":864
},
  "geometry": {"coordinates":[-56.31667,-25.95],"type":"Point"}
}