{
  "type": "Feature",
  "properties": {
    "gn:admin1_code":"1.0",
    "gn:admin2_code":"1002",
    "gn:asciiname":"Tres Fronteras",
    "gn:country_code":"PY",
    "gn:dem":215,
    "gn:feature_class":"P",
    "gn:feature_code":"PPLL",
    "gn:name":"Tres Fronteras",
    "gn:population":0,
    "gn:timezone":"America/Asuncion",
    "iso:country":"PY",
    "name:bre_x_preferred":[
        "Tres Fronteras"
    ],
    "name:deu_x_preferred":[
        "Tres Fronteras"
    ],
    "name:nor_x_preferred":[
        "Tres Fronteras"
    ],
    "name:pol_x_preferred":[
        "Tres Fronteras"
    ],
    "name:por_x_preferred":[
        "Tr\u00eas Fronteiras"
    ],
    "name:rus_x_preferred":[
        "\u0422\u0440\u0435\u0441-\u0424\u0440\u043e\u043d\u0442\u0435\u0440\u0430\u0441"
    ],
    "name:spa_x_preferred":[
        "Tres Fronteras"
    ],
    "name:ukr_x_preferred":[
        "\u0422\u0440\u0435\u0441-\u0424\u0440\u043e\u043d\u0442\u0435\u0440\u0430\u0441"
    ],
    "wof:name":"Tres Fronteras",
    "wof:placetype":"locality"
},
  "geometry": {"coordinates":[-54.60359,-25.57858],"type":"Point"}
}