{
  "type": "Feature",
  "properties": {
    "gn:country":"PY",
    "gn:fcode":"PPLA",
    "gn:population":41157,
    "iso:country":"PY",
    "name:bel_x_preferred":[
        "\u0413\u043e\u0440\u0430\u0434 \u0412\u0456\u043b\u044c\u044f\u0440\u044b\u043a\u0430"
    ],
    "name:bel_x_variant":[
        "\u0412\u0456\u043b\u044c\u044f\u0440\u044b\u043a\u0430"
    ],
    "name:bre_x_preferred":[
        "Villarrica"
    ],
    "name:cat_x_preferred":[
        "Villarrica"
    ],
    "name:ceb_x_preferred":[
        "Villarrica"
    ],
    "name:ces_x_preferred":[
        "Villarrica"
    ],
    "name:deu_x_preferred":[
        "Villarrica"
    ],
    "name:eng_x_preferred":[
        "Villarrica"
    ],
    "name:fas_x_preferred":[
        "\u0648\u06cc\u0627\u0631\u06cc\u06a9\u0627"
    ],
    "name:fra_x_preferred":[
        "Villarrica"
    ],
    "name:grn_x_preferred":[
        "Villarrika"
    ],
    "name:heb_x_preferred":[
        "\u05d5\u05d9\u05d0\u05e8\u05d9\u05e7\u05d4"
    ],
    "name:hun_x_preferred":[
        "Villarrica"
    ],
    "name:isl_x_preferred":[
        "Villarrica"
    ],
    "name:ita_x_preferred":[
        "Villarrica"
    ],
    "name:jpn_x_preferred":[
        "\u30d3\u30b8\u30e3\u30ea\u30ab"
    ],
    "name:kat_x_preferred":[
        "\u10d5\u10d8\u10da\u10d8\u10d0\u10e0\u10d8\u10d9\u10d0"
    ],
    "name:kor_x_preferred":[
        "\ube44\uc57c\ub9ac\uce74"
    ],
    "name:lit_x_preferred":[
        "Viljarika"
    ],
    "name:nld_x_preferred":[
        "Villarrica"
    ],
    "name:pol_x_preferred":[
        "Villarrica"
    ],
    "name:por_x_preferred":[
        "Villarrica"
    ],
    "name:rus_x_preferred":[
        "\u0412\u0438\u043b\u044c\u044f\u0440\u0440\u0438\u043a\u0430"
    ],
    "name:slk_x_preferred":[
        "Villarrica"
    ],
    "name:spa_x_preferred":[
        "Villarrica"
    ],
    "name:swe_x_preferred":[
        "Villarrica"
    ],
    "name:tur_x_preferred":[
        "Villarrica"
    ],
    "name:ukr_x_preferred":[
        "\u0412\u0456\u043b\u044c\u044f\u0440\u0440\u0456\u043a\u0430"
    ],
    "name:und_x_variant":[
        "Villarrica del Esp\u00edritu Santo"
    ],
    "name:urd_x_preferred":[
        "\u0648\u06cc\u0627\u0631\u06cc\u06a9\u0627\u060c \u067e\u06cc\u0631\u0627\u06af\u0648\u0626\u06d2"
    ],
    "name:zho_x_preferred":[
        "\u6bd4\u4e9a\u91cc\u5361"
    ],
    "name:zho_x_variant":[
        "\u6bd4\u4e9e\u91cc\u5361"
    ],
    "qs:gn_pop":0,
    "qs:name":"Villarrica",
    "qs:name_adm0":"Paraguay",
    "qs:name_adm1":"Guair\u00e1",
    "qs:photos":131,
    "qs:photos_1k":27,
    "qs:photos_9k":1,
    "qs:photos_9r":3,
    "qs:photos_all":131,
    "qs:photos_sr":3,
    "qs:placetype":"Town",
    "qs:pop_sr":"0",
    "qs:woe_adm0":23424917,
    "wd:wordcount":52,
    "wof:name":"Villarrica",
    "wof:placetype":"locality",
    "wof:population":41157
},
  "geometry": {"coordinates":[-56.449642,-25.784469],"type":"Point"}
}