{
  "type": "Feature",
  "properties": {
    "gn:admin1_code":"17.0",
    "gn:admin2_code":"0208",
    "gn:asciiname":"Hachita",
    "gn:country_code":"PY",
    "gn:dem":186,
    "gn:feature_class":"P",
    "gn:feature_code":"PPL",
    "gn:name":"Hachita",
    "gn:population":0,
    "gn:timezone":"America/Asuncion",
    "iso:country":"PY",
    "name:spa_x_preferred":[
        "Hachita"
    ],
    "wof:name":"Hachita",
    "wof:placetype":"locality"
},
  "geometry": {"coordinates":[-56.21100000000001,-24.60562],"type":"Point"}
}