{
  "type": "Feature",
  "properties": {
    "gn:admin1_code":"24.0",
    "gn:admin2_code":"1605",
    "gn:asciiname":"Blumengart",
    "gn:country_code":"PY",
    "gn:dem":129,
    "gn:feature_class":"P",
    "gn:feature_code":"PPL",
    "gn:name":"Blumengart",
    "gn:population":0,
    "gn:timezone":"America/Asuncion",
    "iso:country":"PY",
    "wof:name":"Blumengart",
    "wof:placetype":"locality"
},
  "geometry": {"coordinates":[-59.9033,-22.36548],"type":"Point"}
}