{
  "type": "Feature",
  "properties": {
    "gn:admin1_code":"24.0",
    "gn:admin2_code":"1602",
    "gn:asciiname":"Aguilera",
    "gn:country_code":"PY",
    "gn:dem":146,
    "gn:feature_class":"P",
    "gn:feature_code":"PPL",
    "gn:name":"Aguilera",
    "gn:population":0,
    "gn:timezone":"America/Asuncion",
    "iso:country":"PY",
    "wof:name":"Aguilera",
    "wof:placetype":"locality"
},
  "geometry": {"coordinates":[-60.35,-23.25],"type":"Point"}
}