{
  "type": "Feature",
  "properties": {
    "gn:admin1_code":"16.0",
    "gn:admin2_code":"1509",
    "gn:asciiname":"Estancia Tres de Mayo",
    "gn:country_code":"PY",
    "gn:dem":102,
    "gn:feature_class":"P",
    "gn:feature_code":"PPL",
    "gn:name":"Estancia Tres de Mayo",
    "gn:population":0,
    "gn:timezone":"America/Asuncion",
    "iso:country":"PY",
    "wof:name":"Estancia Tres de Mayo",
    "wof:placetype":"locality"
},
  "geometry": {"coordinates":[-59.01667,-24.61667000000001],"type":"Point"}
}